Workbook

Sheet Read me
A1: Gummy & supplement stores – Meta ads tracker
A3: Data collected on | B3: 46300
A4: Countries | B4: Poland, Bulgaria, Romania, Greece, Slovenia, Slovakia, Croatia, Czechia, Hungary (one tab each)
A6: COLUMNS
A7: Store link | B7: The store website (where the ads send people).
A8: Meta Ad Library link | B8: Opens the store's Facebook page in Meta Ad Library (all countries, active + inactive ads). Use it to re-check every number.
A9: Entry price | B9: Lowest price to buy ONE unit of the main product the store advertises (after the discount shown on the site). Local currency; the EUR column converts it with the FX tab.
A10: Offer | B10: The promotion shown on the store / ad landing page at collection time (bundles like 2+1, % off, free shipping threshold, gifts).
A11: Oldest ad in Ad Library | B11: Start date of the oldest ad Meta Ad Library still shows for the page, active or inactive. Best available proxy for when they started advertising.
A12: Ads in Ad Library | B12: Number of ads Meta shows for the page (all countries, active + inactive). Meta rounds big numbers.
A13: Active ads now | B13: Ads running on the collection date.
A14: Oldest live ad: start date | B14: Start date of the longest-running ad that is still active. An ad running for a long time is usually a proven winner.
A15: Days since … | B15: Formulas: Data collected on (cell B3) minus the date. Change B3 to TODAY() if you want them to keep counting.
A17: LIMITATIONS
A18: Ad retention | B18: Meta keeps inactive ads that ran in the EU for about 1 year after they stop (DSA rule). Stores advertising longer than that may have started earlier than 'Oldest ad in Ad Library' shows.
A19: Page vs. store | B19: Counts are per Facebook page. Some brands run one page for several countries (e.g. Bloom Robbins SK/CZ), so the same numbers appear in more than one tab.
A20: Prices | B20: Collected from the store websites on the collection date. Promotions change often.
A21: Selection | B21: Stores were found by searching active Meta ads in each country for local words for gummies and food supplements, plus web searches. It is a list of active advertisers, not a full census.
A22: Blank cell | B22: The value could not be collected (site blocked the scraper, or Meta throttled the lookup). Open the link to check.
A24: COLOUR LEGEND
A25: Blue text | B25: Numbers collected from websites / Meta Ad Library.
A26: Black text | B26: Formulas – do not overwrite.
A27: Yellow cells | B27: Inputs you can edit (collection date, FX rates).

Sheet FX
A1: Exchange rates used for EUR conversion
A2: Approximate rates (assumption, Oct 2026). Edit the yellow cells and every EUR column recalculates. Bulgaria uses EUR since 1 Jan 2026.
A4: Currency | B4: EUR per 1 unit
A5: EUR | B5: 1
A6: PLN | B6: 0.235
A7: RON | B7: 0.197
A8: CZK | B8: 0.0405
A9: HUF | B9: 0.00255
A10: BGN | B10: 0.5113
A11: RSD | B11: 0.00853

Sheet Summary
A1: Summary by country
A3: Country | B3: Stores listed | C3: Stores selling gummies ("Yes…") | D3: Total ads (all stores) | E3: Active ads now (all stores) | F3: Median entry price (EUR) | G3: Store with most ads | H3: Earliest oldest ad
A4: Poland | B4: =COUNTA(Poland!$B$5:$B$16) -> 12 | C4: =COUNTIF(Poland!$F$5:$F$16,"Yes*") -> 5 | D4: =SUM(Poland!$N$5:$N$16) -> 20591 | E4: =SUM(Poland!$O$5:$O$16) -> 2471 | F4: =IFERROR(MEDIAN(Poland!$J$5:$J$16),"") -> 11.337575 | G4: =INDEX(Poland!$B$5:$B$16,MATCH(MAX(Poland!$N$5:$N$16),Poland!$N$5:$N$16,0)) -> NOYO | H4: =IF(COUNT(Poland!$L$5:$L$16)=0,"",MIN(Poland!$L$5:$L$16)) -> 44736
A5: Bulgaria | B5: =COUNTA(Bulgaria!$B$5:$B$14) -> 10 | C5: =COUNTIF(Bulgaria!$F$5:$F$14,"Yes*") -> 9 | D5: =SUM(Bulgaria!$N$5:$N$14) -> 8616 | E5: =SUM(Bulgaria!$O$5:$O$14) -> 937 | F5: =IFERROR(MEDIAN(Bulgaria!$J$5:$J$14),"") -> 19.89 | G5: =INDEX(Bulgaria!$B$5:$B$14,MATCH(MAX(Bulgaria!$N$5:$N$14),Bulgaria!$N$5:$N$14,0)) -> FutuNatura.bg | H5: =IF(COUNT(Bulgaria!$L$5:$L$14)=0,"",MIN(Bulgaria!$L$5:$L$14)) -> 44441
A6: Romania | B6: =COUNTA(Romania!$B$5:$B$12) -> 8 | C6: =COUNTIF(Romania!$F$5:$F$12,"Yes*") -> 5 | D6: =SUM(Romania!$N$5:$N$12) -> 5763 | E6: =SUM(Romania!$O$5:$O$12) -> 294 | F6: =IFERROR(MEDIAN(Romania!$J$5:$J$12),"") -> 20.882 | G6: =INDEX(Romania!$B$5:$B$12,MATCH(MAX(Romania!$N$5:$N$12),Romania!$N$5:$N$12,0)) -> FutuNatura.ro | H6: =IF(COUNT(Romania!$L$5:$L$12)=0,"",MIN(Romania!$L$5:$L$12)) -> 45481
A7: Greece | B7: =COUNTA(Greece!$B$5:$B$12) -> 8 | C7: =COUNTIF(Greece!$F$5:$F$12,"Yes*") -> 5 | D7: =SUM(Greece!$N$5:$N$12) -> 4547 | E7: =SUM(Greece!$O$5:$O$12) -> 285 | F7: =IFERROR(MEDIAN(Greece!$J$5:$J$12),"") -> 13.92 | G7: =INDEX(Greece!$B$5:$B$12,MATCH(MAX(Greece!$N$5:$N$12),Greece!$N$5:$N$12,0)) -> FutuNatura.gr | H7: =IF(COUNT(Greece!$L$5:$L$12)=0,"",MIN(Greece!$L$5:$L$12)) -> 45308
A8: Slovenia | B8: =COUNTA(Slovenia!$B$5:$B$11) -> 7 | C8: =COUNTIF(Slovenia!$F$5:$F$11,"Yes*") -> 3 | D8: =SUM(Slovenia!$N$5:$N$11) -> 19634 | E8: =SUM(Slovenia!$O$5:$O$11) -> 1581 | F8: =IFERROR(MEDIAN(Slovenia!$J$5:$J$11),"") -> 22.57 | G8: =INDEX(Slovenia!$B$5:$B$11,MATCH(MAX(Slovenia!$N$5:$N$11),Slovenia!$N$5:$N$11,0)) -> Golden Tree Slovenija | H8: =IF(COUNT(Slovenia!$L$5:$L$11)=0,"",MIN(Slovenia!$L$5:$L$11)) -> 43941
A9: Slovakia | B9: =COUNTA(Slovakia!$B$5:$B$10) -> 6 | C9: =COUNTIF(Slovakia!$F$5:$F$10,"Yes*") -> 5 | D9: =SUM(Slovakia!$N$5:$N$10) -> 11809 | E9: =SUM(Slovakia!$O$5:$O$10) -> 981 | F9: =IFERROR(MEDIAN(Slovakia!$J$5:$J$10),"") -> 22.47 | G9: =INDEX(Slovakia!$B$5:$B$10,MATCH(MAX(Slovakia!$N$5:$N$10),Slovakia!$N$5:$N$10,0)) -> Bloom Robbins SK/CZ | H9: =IF(COUNT(Slovakia!$L$5:$L$10)=0,"",MIN(Slovakia!$L$5:$L$10)) -> 45349
A10: Croatia | B10: =COUNTA(Croatia!$B$5:$B$12) -> 8 | C10: =COUNTIF(Croatia!$F$5:$F$12,"Yes*") -> 3 | D10: =SUM(Croatia!$N$5:$N$12) -> 16054 | E10: =SUM(Croatia!$O$5:$O$12) -> 1378 | F10: =IFERROR(MEDIAN(Croatia!$J$5:$J$12),"") -> 18.83535 | G10: =INDEX(Croatia!$B$5:$B$12,MATCH(MAX(Croatia!$N$5:$N$12),Croatia!$N$5:$N$12,0)) -> Carnium Botanicals Hrvatska | H10: =IF(COUNT(Croatia!$L$5:$L$12)=0,"",MIN(Croatia!$L$5:$L$12)) -> 45155
A11: Czechia | B11: =COUNTA(Czechia!$B$5:$B$12) -> 8 | C11: =COUNTIF(Czechia!$F$5:$F$12,"Yes*") -> 3 | D11: =SUM(Czechia!$N$5:$N$12) -> 18584 | E11: =SUM(Czechia!$O$5:$O$12) -> 1082 | F11: =IFERROR(MEDIAN(Czechia!$J$5:$J$12),"") -> 16.4575 | G11: =INDEX(Czechia!$B$5:$B$12,MATCH(MAX(Czechia!$N$5:$N$12),Czechia!$N$5:$N$12,0)) -> Bloom Robbins SK/CZ | H11: =IF(COUNT(Czechia!$L$5:$L$12)=0,"",MIN(Czechia!$L$5:$L$12)) -> 45118
A12: Hungary | B12: =COUNTA(Hungary!$B$5:$B$12) -> 8 | C12: =COUNTIF(Hungary!$F$5:$F$12,"Yes*") -> 7 | D12: =SUM(Hungary!$N$5:$N$12) -> 2862 | E12: =SUM(Hungary!$O$5:$O$12) -> 431 | F12: =IFERROR(MEDIAN(Hungary!$J$5:$J$12),"") -> 22.9245 | G12: =INDEX(Hungary!$B$5:$B$12,MATCH(MAX(Hungary!$N$5:$N$12),Hungary!$N$5:$N$12,0)) -> Obstermann's (termeszetesgumicukor.hu) | H12: =IF(COUNT(Hungary!$L$5:$L$12)=0,"",MIN(Hungary!$L$5:$L$12)) -> 44673

Sheet Poland
A1: Poland – stores selling gummies / supplements with Meta ads
A2: 12 stores · Meta data collected on the date in 'Read me'!B3 · sorted by number of ads
A4: # | B4: Store | C4: Store link | D4: Meta Ad Library link | E4: What they sell | F4: Sells gummies? | G4: Entry product | H4: Entry price (local) | I4: Currency | J4: Entry price (EUR) | K4: Offer | L4: Oldest ad in Ad Library (active or not) | M4: Days since oldest ad | N4: Ads in Ad Library (total) | O4: Active ads now | P4: Oldest live ad: start date | Q4: Days since oldest live ad | R4: Notes
A5: 1 | B5: NOYO | C5: https://noyopharm.com | D5: Open Ad Library | E5: Slimming & beauty supplements + cosmetics | F5: No (capsules/powders) | G5: Detox supplement | H5: 129 | I5: PLN | J5: =IF(H5="","",H5*INDEX(FX!$B$5:$B$11,MATCH(I5,FX!$A$5:$A$11,0))) -> 30.315 | K5: "Autumn with NOYO" promo; bundles (Flat Belly, Bestseller); −10% first order; free delivery from 300 zł | L5: 45849 | M5: =IF(L5="","",'Read me'!$B$3-L5) -> 451 | N5: 9071 | O5: 689 | P5: 46186 | Q5: =IF(P5="","",'Read me'!$B$3-P5) -> 114
A6: 2 | B6: NUTRIDOME (Oh!Tomi) | C6: https://nutridome.pl | D6: Open Ad Library | E6: Beauty shop: Oh!Tomi gummies (hair, sleep), collagen, cosmetics | F6: Yes (Oh!Tomi) | G6: Oh!Tomi Super Hair gummies, 60 pcs (advertised) | H6: 64.99 | I6: PLN | J6: =IF(H6="","",H6*INDEX(FX!$B$5:$B$11,MATCH(I6,FX!$A$5:$A$11,0))) -> 15.27265 | K6: Small markdown (69.00 → 64.99 zł); −10% subscribe & save; free delivery from 180 zł | L6: 45672 | M6: =IF(L6="","",'Read me'!$B$3-L6) -> 628 | N6: 5439 | O6: 1017 | P6: 45860 | Q6: =IF(P6="","",'Read me'!$B$3-P6) -> 440
A7: 3 | B7: Labify.pl | C7: https://labify.pl | D7: Open Ad Library | E7: Own-brand supplements for men & women, incl. vitamin C gummies | F7: Yes (vit C gummies) | G7: Vitamin C gummies | H7: 49 | I7: PLN | J7: =IF(H7="","",H7*INDEX(FX!$B$5:$B$11,MATCH(I7,FX!$A$5:$A$11,0))) -> 11.515 | K7: Early access to promotions via newsletter | L7: 45819 | M7: =IF(L7="","",'Read me'!$B$3-L7) -> 481 | N7: 2305 | O7: 233 | P7: 46225 | Q7: =IF(P7="","",'Read me'!$B$3-P7) -> 75
A8: 4 | B8: Sundose | C8: https://sundose.com | D8: Open Ad Library | E8: Personalised daily vitamin sachets (subscription, dietitian + app) | F8: No (sachets) | G8: Personalised sachets, 30 days – first month | H8: 99 | I8: PLN | J8: =IF(H8="","",H8*INDEX(FX!$B$5:$B$11,MATCH(I8,FX!$A$5:$A$11,0))) -> 23.265 | K8: First month 99 zł, then ~200 zł/month; price range 50–230 zł depending on formula | L8: 45911 | M8: =IF(L8="","",'Read me'!$B$3-L8) -> 389 | N8: 1190 | O8: 48 | P8: 46191 | Q8: =IF(P8="","",'Read me'!$B$3-P8) -> 109 | R8: Price from public reviews/discount pages, not scraped from the checkout.
A9: 5 | B9: Noble Health | C9: https://noblehealth.pl | D9: Open Ad Library | E9: Gummies ("Misie" bears: hair, sleep, stress, skin; Hair Care Panda) | F9: Yes – main line | G9: Misie gummies (hair / stress / sleep) | H9: 47.49 | I9: PLN | J9: =IF(H9="","",H9*INDEX(FX!$B$5:$B$11,MATCH(I9,FX!$A$5:$A$11,0))) -> 11.16015 | K9: Hair Care Panda −30% (save 45 zł → 105 zł); bundles; free delivery from 200 zł | L9: 45872 | M9: =IF(L9="","",'Read me'!$B$3-L9) -> 428 | N9: 1000 | O9: 138 | P9: 45993 | Q9: =IF(P9="","",'Read me'!$B$3-P9) -> 307 | R9: Also advertises in CZ.
A10: 6 | B10: FEZI | C10: https://fezi.pl | D10: Open Ad Library | E10: Apple-cider-vinegar gummies & other gummy supplements | F10: Yes – gummies only | G10: FEZI Apple Cider Vinegar gummies, 60 pcs (30 days) | H10: 119.99 | I10: PLN | J10: =IF(H10="","",H10*INDEX(FX!$B$5:$B$11,MATCH(I10,FX!$A$5:$A$11,0))) -> 28.19765 | K10: Birthday promo 2+1 FREE; 3+2 FREE; free delivery; 169.99 → 119.99 zł | L10: 45974 | M10: =IF(L10="","",'Read me'!$B$3-L10) -> 326 | N10: 704 | O10: 130 | P10: 46041 | Q10: =IF(P10="","",'Read me'!$B$3-P10) -> 259
A11: 7 | B11: OstroVit | C11: https://ostrovit.com | D11: Open Ad Library | E11: Sports nutrition & vitamins (huge catalogue) | F11: Some | G11: Magnesium glycinate 90 caps | H11: 24.99 | I11: PLN | J11: =IF(H11="","",H11*INDEX(FX!$B$5:$B$11,MATCH(I11,FX!$A$5:$A$11,0))) -> 5.87265 | K11: −10% newsletter code; bundles | L11: 45494 | M11: =IF(L11="","",'Read me'!$B$3-L11) -> 806 | N11: 549 | O11: 157 | P11: 45494 | Q11: =IF(P11="","",'Read me'!$B$3-P11) -> 806
A12: 8 | B12: Narum | C12: https://mynarum.com | D12: Open Ad Library | E12: Premium supplements (iron, magnesium, selenium, omega, collagen) | F12: No | G12: Omega Forte (on promotion) | I12: PLN | J12: =IF(H12="","",H12*INDEX(FX!$B$5:$B$11,MATCH(I12,FX!$A$5:$A$11,0))) | K12: "In promotion" items (e.g. Omega Forte 29.99 → 25.99 € on the EUR site) | L12: 45912 | M12: =IF(L12="","",'Read me'!$B$3-L12) -> 388 | N12: 221 | O12: 41 | P12: 45922 | Q12: =IF(P12="","",'Read me'!$B$3-P12) -> 378 | R12: Site showed EUR prices to the scraper; PLN price not captured.
A13: 9 | B13: Real Pharm Nutrition | C13: https://realpharm.eu | D13: Open Ad Library | E13: Polish sports-nutrition & supplements producer | F13: No | G13: CitruArgin citrulline-arginine 150 caps (advertised) | H13: 39 | I13: PLN | J13: =IF(H13="","",H13*INDEX(FX!$B$5:$B$11,MATCH(I13,FX!$A$5:$A$11,0))) -> 9.165 | K13: Promo set CitruArgin 300 g + shaker 53.99 zł (was 61.99); −10% first order; free shipping from 99 zł | L13: 45803 | M13: =IF(L13="","",'Read me'!$B$3-L13) -> 497 | N13: 67 | O13: 4 | P13: 46098 | Q13: =IF(P13="","",'Read me'!$B$3-P13) -> 202
A14: 10 | B14: Panda Care | C14: https://pandacare.pl | D14: Open Ad Library | E14: Multi-brand supplement & health-food shop | F14: Some | G14: Para Farm drops (offer) | H14: 36.97 | I14: PLN | J14: =IF(H14="","",H14*INDEX(FX!$B$5:$B$11,MATCH(I14,FX!$A$5:$A$11,0))) -> 8.68795 | K14: Weekly hits with discounts; free delivery from 199 zł | L14: 45870 | M14: =IF(L14="","",'Read me'!$B$3-L14) -> 430 | N14: 19 | O14: 5 | P14: 46240 | Q14: =IF(P14="","",'Read me'!$B$3-P14) -> 60
A15: 11 | B15: Healthy Now | C15: https://trichonex.doctorzakaria.com/l | D15: Open Ad Library | E15: Advertorial/COD funnels for supplements (Trichonex hair-loss, Collagen Complex) | F15: No (capsules) | I15: PLN | J15: =IF(H15="","",H15*INDEX(FX!$B$5:$B$11,MATCH(I15,FX!$A$5:$A$11,0))) | K15: "Buy now with discount" countdown; free sample programme (Collagen Complex); free delivery | L15: 46285 | M15: =IF(L15="","",'Read me'!$B$3-L15) -> 15 | N15: 18 | O15: 2 | P15: 46295 | Q15: =IF(P15="","",'Read me'!$B$3-P15) -> 5 | R15: Not a classic store: ads lead to "doctor" advertorial pages with order forms.
A16: 12 | B16: HelloGummies | C16: https://hellogummies.pl | D16: Open Ad Library | E16: Vitamin gummies (hair & nails, beta-carotene, collagen, sleep, kids) | F16: Yes – gummies only | G16: Sleep Well melatonin gummies | H16: 19.99 | I16: PLN | J16: =IF(H16="","",H16*INDEX(FX!$B$5:$B$11,MATCH(I16,FX!$A$5:$A$11,0))) -> 4.69765 | K16: −15% with code JESIEŃ (in ads); bundles (zestawy); free delivery from 150 zł | L16: 44736 | M16: =IF(L16="","",'Read me'!$B$3-L16) -> 1564 | N16: 8 | O16: 7 | P16: 44736 | Q16: =IF(P16="","",'Read me'!$B$3-P16) -> 1564

Sheet Bulgaria
A1: Bulgaria – stores selling gummies / supplements with Meta ads
A2: 10 stores · Meta data collected on the date in 'Read me'!B3 · sorted by number of ads
A4: # | B4: Store | C4: Store link | D4: Meta Ad Library link | E4: What they sell | F4: Sells gummies? | G4: Entry product | H4: Entry price (local) | I4: Currency | J4: Entry price (EUR) | K4: Offer | L4: Oldest ad in Ad Library (active or not) | M4: Days since oldest ad | N4: Ads in Ad Library (total) | O4: Active ads now | P4: Oldest live ad: start date | Q4: Days since oldest live ad | R4: Notes
A5: 1 | B5: FutuNatura.bg | C5: https://www.futunatura.bg | D5: Open Ad Library | E5: Own-brand supplements incl. creatine & kids gummies | F5: Yes (part of range) | G5: Creatine gummies 3000 mg, 90 pcs (advertised) | H5: 17.99 | I5: EUR | J5: =IF(H5="","",H5*INDEX(FX!$B$5:$B$11,MATCH(I5,FX!$A$5:$A$11,0))) -> 17.99 | K5: Weekly −15% on everything; quantity discount; free delivery over 39.99 €; gift over 50 € | L5: 45547 | M5: =IF(L5="","",'Read me'!$B$3-L5) -> 753 | N5: 2922 | O5: 82 | P5: 46136 | Q5: =IF(P5="","",'Read me'!$B$3-P5) -> 164
A6: 2 | B6: Gymbeam.bg | C6: https://gymbeam.bg | D6: Open Ad Library | E6: Sports nutrition & supplements (incl. "Yummies" gummies: multivitamin, creatine, ashwagandha…) | F6: Yes (Yummies line) | G6: Multivitamin Yummies, 60 gummies | H6: 7.5 | I6: EUR | J6: =IF(H6="","",H6*INDEX(FX!$B$5:$B$11,MATCH(I6,FX!$A$5:$A$11,0))) -> 7.5 | K6: Creatine Yummies 19.50 €; site promos (Cloudflare blocked our scraper – check the link for current offers) | L6: 44441 | M6: =IF(L6="","",'Read me'!$B$3-L6) -> 1859 | N6: 2431 | O6: 235 | P6: 45890 | Q6: =IF(P6="","",'Read me'!$B$3-P6) -> 410
A7: 3 | B7: Glow Gummies | C7: https://tryglowgummies.com | D7: Open Ad Library | E7: Tanning gummies (international English-language DTC brand) | F7: Yes – gummies only | G7: Glow tanning gummies, 1 pack | I7: EUR | J7: =IF(H7="","",H7*INDEX(FX!$B$5:$B$11,MATCH(I7,FX!$A$5:$A$11,0))) | K7: Bundle discounts + extra 5% for subscribers; free shipping; 12-week money-back guarantee | L7: 46108 | M7: =IF(L7="","",'Read me'!$B$3-L7) -> 192 | N7: 1866 | O7: 430 | P7: 46108 | Q7: =IF(P7="","",'Read me'!$B$3-P7) -> 192 | R7: Not a Bulgarian store: an international brand whose ads also reach BG and HR. The shop showed 71.60 AUD (geo-priced) to our scraper, so no EUR price recorded.
A8: 4 | B8: Шиладжит Прайм (Shilajit Prime) | C8: https://shilajit-prime.shop | D8: Open Ad Library | E8: Shilajit resin/supplement (single-product store) | F8: No (resin) | G8: Shilajit – 1 jar, 30 days | H8: 24.97 | I8: EUR | J8: =IF(H8="","",H8*INDEX(FX!$B$5:$B$11,MATCH(I8,FX!$A$5:$A$11,0))) -> 24.97 | K8: Save 10 € (34.97 → 24.97 €); multi-pack bundles ("choose your package") | L8: 46108 | M8: =IF(L8="","",'Read me'!$B$3-L8) -> 192 | N8: 590 | O8: 77 | P8: 46286 | Q8: =IF(P8="","",'Read me'!$B$3-P8) -> 14
A9: 5 | B9: Flow Vitamins | C9: https://vitaminsflow.com | D9: Open Ad Library | E9: Women's gummies: PMS, intimate health probiotics, ACV bears | F9: Yes – gummies only | G9: Probiotic bears for women's health, 30 days | H9: 25.52 | I9: EUR | J9: =IF(H9="","",H9*INDEX(FX!$B$5:$B$11,MATCH(I9,FX!$A$5:$A$11,0))) -> 25.52 | K9: Buy 2 + 1 FREE; 3 + 2; subscribe −15% / −40%; free delivery over 65 € | L9: 45688 | M9: =IF(L9="","",'Read me'!$B$3-L9) -> 612 | N9: 380 | O9: 63 | P9: 45885 | Q9: =IF(P9="","",'Read me'!$B$3-P9) -> 415
A10: 6 | B10: Nature's Way България | C10: https://naturesway.bg | D10: Open Ad Library | E10: Nature's Way / Alive! multivitamins incl. gummies | F10: Yes (Alive! gummies) | G10: Alive! kids multivitamin, 40 gummies | H10: 11.89 | I10: EUR | J10: =IF(H10="","",H10*INDEX(FX!$B$5:$B$11,MATCH(I10,FX!$A$5:$A$11,0))) -> 11.89 | K10: Up to −50/−60% on Alive!; promo packs (Women + Men); free delivery over 40 € | L10: 44673 | M10: =IF(L10="","",'Read me'!$B$3-L10) -> 1627 | N10: 159 | O10: 8 | P10: 45875 | Q10: =IF(P10="","",'Read me'!$B$3-P10) -> 425
A11: 7 | B11: Vital Gummy | C11: https://vitalgummy.com | D11: Open Ad Library | E11: Women's gummies: hair vitamins, ACV, good-night | F11: Yes – gummies only | G11: Apple Cider Vinegar gummies, 1 month | H11: 22 | I11: EUR | J11: =IF(H11="","",H11*INDEX(FX!$B$5:$B$11,MATCH(I11,FX!$A$5:$A$11,0))) -> 22 | K11: Buy 1 + 1 FREE for 29 € + free book; 2+2 and 3+3 free; free delivery over 35.80 € | L11: 45229 | M11: =IF(L11="","",'Read me'!$B$3-L11) -> 1071 | N11: 95 | O11: 24 | P11: 46238 | Q11: =IF(P11="","",'Read me'!$B$3-P11) -> 62
A12: 8 | B12: The Ceel Bulgaria | C12: https://theceel.bg | D12: Open Ad Library | E12: Beauty sets + vegan gummy vitamins (skin, hair, sleep, collagen, matcha) | F12: Yes (gummies collection) | G12: Vegan gummy vitamins (any), 1 pack | H12: 19.89 | I12: EUR | J12: =IF(H12="","",H12*INDEX(FX!$B$5:$B$11,MATCH(I12,FX!$A$5:$A$11,0))) -> 19.89 | K12: Sale prices on sets (e.g. 66.46 → 53.17 €); free delivery over 51.13 € | L12: 45916 | M12: =IF(L12="","",'Read me'!$B$3-L12) -> 384 | N12: 89 | O12: 0 | Q12: =IF(P12="","",'Read me'!$B$3-P12) | R12: No active ads on the collection date (Meta returned none in repeated checks).
A13: 9 | B13: Leyra | C13: https://leyra.bg | D13: Open Ad Library | E13: Women's intimate-health gummies (Flora) | F13: Yes – gummies only | G13: Flora gummy bears, 60 pcs (30 days) | H13: 25.99 | I13: EUR | J13: =IF(H13="","",H13*INDEX(FX!$B$5:$B$11,MATCH(I13,FX!$A$5:$A$11,0))) -> 25.99 | K13: Summer sale up to −45% (34.25 → 25.99 €); Buy 2 + 1 FREE; 3 + 2 FREE; free delivery | L13: 46051 | M13: =IF(L13="","",'Read me'!$B$3-L13) -> 249 | N13: 69 | O13: 16 | P13: 46245 | Q13: =IF(P13="","",'Read me'!$B$3-P13) -> 55
A14: 10 | B14: Alive Multivitamins (revita.bg) | C14: https://revita.bg | D14: Open Ad Library | E14: Herbal & supplement shop; Alive! gummy multivitamins | F14: Yes (Alive! gummies) | G14: Alive! kids chewable multivitamin, 30 pcs | H14: 7.06 | I14: EUR | J14: =IF(H14="","",H14*INDEX(FX!$B$5:$B$11,MATCH(I14,FX!$A$5:$A$11,0))) -> 7.06 | K14: −15% on Alive! kids; free delivery over 40 € | L14: 45160 | M14: =IF(L14="","",'Read me'!$B$3-L14) -> 1140 | N14: 15 | O14: 2 | P14: 46175 | Q14: =IF(P14="","",'Read me'!$B$3-P14) -> 125

Sheet Romania
A1: Romania – stores selling gummies / supplements with Meta ads
A2: 8 stores · Meta data collected on the date in 'Read me'!B3 · sorted by number of ads
A4: # | B4: Store | C4: Store link | D4: Meta Ad Library link | E4: What they sell | F4: Sells gummies? | G4: Entry product | H4: Entry price (local) | I4: Currency | J4: Entry price (EUR) | K4: Offer | L4: Oldest ad in Ad Library (active or not) | M4: Days since oldest ad | N4: Ads in Ad Library (total) | O4: Active ads now | P4: Oldest live ad: start date | Q4: Days since oldest live ad | R4: Notes
A5: 1 | B5: FutuNatura.ro | C5: https://www.futunatura.ro | D5: Open Ad Library | E5: Own-brand supplements: magnesium, omega-3, creatine gummies, kids gummies | F5: Yes (part of range) | G5: Creatine monohydrate gummies 3000 mg, 90 pcs (advertised) | H5: 82.99 | I5: RON | J5: =IF(H5="","",H5*INDEX(FX!$B$5:$B$11,MATCH(I5,FX!$A$5:$A$11,0))) -> 16.34903 | K5: Weekly offer −15% on everything; quantity discounts; free delivery over 199 lei; free gift over 249 lei | L5: 45588 | M5: =IF(L5="","",'Read me'!$B$3-L5) -> 712 | N5: 3044 | O5: 53 | P5: 46135 | Q5: =IF(P5="","",'Read me'!$B$3-P5) -> 165
A6: 2 | B6: Hairburst Romania | C6: https://www.hairburst.com/ro-ro | D6: Open Ad Library | E6: Hair-growth gummies, vitamins, shampoos (UK brand, RO page) | F6: Yes – hero product | G6: Chewable hair vitamins (gummies), 1 month | H6: 148 | I6: RON | J6: =IF(H6="","",H6*INDEX(FX!$B$5:$B$11,MATCH(I6,FX!$A$5:$A$11,0))) -> 29.156 | K6: Buy one, get one free (ad landing page); 399 → 148 RON; 3-month stock −30% (279 RON); free delivery; 90-day money-back | L6: 45853 | M6: =IF(L6="","",'Read me'!$B$3-L6) -> 447 | N6: 914 | O6: 56 | P6: 46251 | Q6: =IF(P6="","",'Read me'!$B$3-P6) -> 49
A7: 3 | B7: Sănătate La Tine Acasă (Doppelherz RO shop) | C7: https://www.sanatatelatineacasa.ro | D7: Open Ad Library | E7: Doppelherz supplements online shop (tablets, capsules, gummies for hair/skin/nails) | F7: Some (Doppelherz gummies) | G7: Cheapest supplement on the homepage (60 tablets) | H7: 24.5 | I7: RON | J7: =IF(H7="","",H7*INDEX(FX!$B$5:$B$11,MATCH(I7,FX!$A$5:$A$11,0))) -> 4.8265 | K7: Promo/cure packs (e.g. −20% bundles); free delivery over 250 lei; 3% newsletter voucher | L7: 45820 | M7: =IF(L7="","",'Read me'!$B$3-L7) -> 480 | N7: 717 | O7: 37 | P7: 46107 | Q7: =IF(P7="","",'Read me'!$B$3-P7) -> 193
A8: 4 | B8: Rootful | C8: https://www.rootfulnutrition.com | D8: Open Ad Library | E8: Own-brand gummies (ACV & kombucha, vit C+zinc+D3, melatonin, ashwagandha, D3) + capsule blends | F8: Yes | G8: Apple Cider Vinegar & Kombucha gummies, 1 pouch | H8: 109 | I8: RON | J8: =IF(H8="","",H8*INDEX(FX!$B$5:$B$11,MATCH(I8,FX!$A$5:$A$11,0))) -> 21.473 | K8: Buy 2 + 1 FREE (72 lei/pouch) or Buy 3 + 2 FREE; free shipping from 195 lei; −10% first order via newsletter | L8: 46142 | M8: =IF(L8="","",'Read me'!$B$3-L8) -> 158 | N8: 372 | O8: 89 | P8: 46205 | Q8: =IF(P8="","",'Read me'!$B$3-P8) -> 95
A9: 5 | B9: Weider.ro | C9: https://www.weider.ro | D9: Open Ad Library | E9: Sports nutrition: whey, creatine, bars, drinks | F9: No | G9: Pure Creatine Powder 250 g | H9: 103 | I9: RON | J9: =IF(H9="","",H9*INDEX(FX!$B$5:$B$11,MATCH(I9,FX!$A$5:$A$11,0))) -> 20.291 | K9: Free delivery on orders from 250 lei | L9: 45553 | M9: =IF(L9="","",'Read me'!$B$3-L9) -> 747 | N9: 328 | O9: 16 | P9: 46143 | Q9: =IF(P9="","",'Read me'!$B$3-P9) -> 157
A10: 6 | B10: Nutrizma.ro | C10: https://nutrizma.ro | D10: Open Ad Library | E10: Creatine gummy cubes | F10: Yes – creatine gummies | G10: Creatine gummy cubes, 90 pcs (30 days) | H10: 136.99 | I10: RON | J10: =IF(H10="","",H10*INDEX(FX!$B$5:$B$11,MATCH(I10,FX!$A$5:$A$11,0))) -> 26.98703 | K10: Volume pricing: 2 packs 256.99 lei (save 16.99), cheaper per pack with 3 | L10: 46087 | M10: =IF(L10="","",'Read me'!$B$3-L10) -> 213 | N10: 325 | O10: 32 | P10: 46126 | Q10: =IF(P10="","",'Read me'!$B$3-P10) -> 174
A11: 7 | B11: TummyTox.ro | C11: https://www.tummytox.ro | D11: Open Ad Library | E11: Women's weight-loss, hormone-balance & beauty supplements (capsules, teas, gummies) | F11: Some (multivitamin gummies) | G11: Hormone Balance – 2 boxes (1+1 FREE, advertised) | H11: 159.99 | I11: RON | J11: =IF(H11="","",H11*INDEX(FX!$B$5:$B$11,MATCH(I11,FX!$A$5:$A$11,0))) -> 31.51803 | K11: 1+1 FREE / −43% to −47% on advertised packs; extra −15% with subscription; free shipping over 199 RON; free gift over 248 RON; 30-day money-back | L11: 45481 | M11: =IF(L11="","",'Read me'!$B$3-L11) -> 819 | N11: 36 | O11: 11 | P11: 45629 | Q11: =IF(P11="","",'Read me'!$B$3-P11) -> 671
A12: 8 | B12: Gummy.ro | C12: https://www.gummy.ro | D12: Open Ad Library | E12: Gummy-only shop (TooMax gummies): vitamin C, D3+K2, melatonin, omega, immunity, kids multivitamins | F12: Yes – gummies only | G12: TooMax Gummy Vitamin C 250 | H12: 57.9 | I12: RON | J12: =IF(H12="","",H12*INDEX(FX!$B$5:$B$11,MATCH(I12,FX!$A$5:$A$11,0))) -> 11.4063 | K12: Sitewide markdowns of −21% to −35% (e.g. Vitamin C 79.90 → 57.90 RON) | L12: 46270 | M12: =IF(L12="","",'Read me'!$B$3-L12) -> 30 | N12: 27 | O12: 0 | Q12: =IF(P12="","",'Read me'!$B$3-P12) | R12: No active ads on the collection date.

Sheet Greece
A1: Greece – stores selling gummies / supplements with Meta ads
A2: 8 stores · Meta data collected on the date in 'Read me'!B3 · sorted by number of ads
A4: # | B4: Store | C4: Store link | D4: Meta Ad Library link | E4: What they sell | F4: Sells gummies? | G4: Entry product | H4: Entry price (local) | I4: Currency | J4: Entry price (EUR) | K4: Offer | L4: Oldest ad in Ad Library (active or not) | M4: Days since oldest ad | N4: Ads in Ad Library (total) | O4: Active ads now | P4: Oldest live ad: start date | Q4: Days since oldest live ad | R4: Notes
A5: 1 | B5: FutuNatura.gr | C5: https://www.futunatura.gr | D5: Open Ad Library | E5: Own-brand supplements incl. creatine & kids gummies | F5: Yes (part of range) | G5: Creatine monohydrate gummies 3000 mg, 90 pcs (advertised) | H5: 14.99 | I5: EUR | J5: =IF(H5="","",H5*INDEX(FX!$B$5:$B$11,MATCH(I5,FX!$A$5:$A$11,0))) -> 14.99 | K5: Weekly −15% on everything (19.99 → 14.99 €); free shipping over 39.99 €; gift over 50 € | L5: 45568 | M5: =IF(L5="","",'Read me'!$B$3-L5) -> 732 | N5: 3378 | O5: 108 | P5: 46193 | Q5: =IF(P5="","",'Read me'!$B$3-P5) -> 107
A6: 2 | B6: vita4you.gr | C6: https://www.vita4you.gr | D6: Open Ad Library | E6: Large online pharmacy: vitamins, supplements, cosmetics (multi-brand) | F6: Yes (multi-brand gummies) | G6: PharmaLead D3 & K2 & Magnesium complex 60 caps (featured) | H6: 21.71 | I6: EUR | J6: =IF(H6="","",H6*INDEX(FX!$B$5:$B$11,MATCH(I6,FX!$A$5:$A$11,0))) -> 21.71 | K6: Free shipping over 59 €; free pick-up; gifts with selected products | L6: 45458 | M6: =IF(L6="","",'Read me'!$B$3-L6) -> 842 | N6: 406 | O6: 58 | P6: 46071 | Q6: =IF(P6="","",'Read me'!$B$3-P6) -> 229
A7: 3 | B7: Naturesplusgreece | C7: https://linktr.ee/naturesplusgr | D7: Open Ad Library | E7: Nature's Plus supplements incl. biotin & collagen gummies | F7: Yes (biotin gummies) | I7: EUR | J7: =IF(H7="","",H7*INDEX(FX!$B$5:$B$11,MATCH(I7,FX!$A$5:$A$11,0))) | K7: Beauty combo (Biotin Gummies + Collagen) in ads | L7: 45855 | M7: =IF(L7="","",'Read me'!$B$3-L7) -> 445 | N7: 287 | O7: 42 | P7: 46126 | Q7: =IF(P7="","",'Read me'!$B$3-P7) -> 174 | R7: Brand page (Nature's Plus distributor); ads point to a link-in-bio page and partner pharmacies, so no single entry price.
A8: 4 | B8: Pharm16.gr | C8: https://www.pharm16.gr | D8: Open Ad Library | E8: Online pharmacy, 50,000+ products incl. supplements | F8: Some | I8: EUR | J8: =IF(H8="","",H8*INDEX(FX!$B$5:$B$11,MATCH(I8,FX!$A$5:$A$11,0))) | K8: Promo packs & limited offers; loyalty points | L8: 45308 | M8: =IF(L8="","",'Read me'!$B$3-L8) -> 992 | N8: 163 | O8: 23 | P8: 45308 | Q8: =IF(P8="","",'Read me'!$B$3-P8) -> 992 | R8: Online pharmacy with 50,000+ products; homepage shows promos but no single hero product.
A9: 5 | B9: myelements | C9: https://www.skroutz.gr/s/25692083/ | D9: Open Ad Library | E9: Magnesium + B6 and multivitamin effervescent tablets (brand sold via pharmacies) | F9: No (effervescent tablets) | G9: Magnesium & B6, 20 effervescent tablets (pharmacy price) | H9: 7.68 | I9: EUR | J9: =IF(H9="","",H9*INDEX(FX!$B$5:$B$11,MATCH(I9,FX!$A$5:$A$11,0))) -> 7.68 | K9: Duo packs (Magnesium + VitaminAll 20+20) | L9: 45931 | M9: =IF(L9="","",'Read me'!$B$3-L9) -> 369 | N9: 141 | O9: 8 | P9: 46272 | Q9: =IF(P9="","",'Read me'!$B$3-P9) -> 28 | R9: Ads link to the Facebook page; the brand sells through pharmacies (price range 7.48–8.87 €).
A10: 6 | B10: Pharmaspot.gr | C10: https://www.pharmaspot.gr | D10: Open Ad Library | E10: Online pharmacy: vitamins, gummies, cosmetics | F10: Yes (multi-brand gummies) | G10: Adult multivitamin gummies, 60 pcs | H10: 13.8 | I10: EUR | J10: =IF(H10="","",H10*INDEX(FX!$B$5:$B$11,MATCH(I10,FX!$A$5:$A$11,0))) -> 13.8 | K10: Promo packs (1+1, gifts); free shipping over 49.90 € | L10: 45346 | M10: =IF(L10="","",'Read me'!$B$3-L10) -> 954 | N10: 117 | O10: 30 | P10: 45776 | Q10: =IF(P10="","",'Read me'!$B$3-P10) -> 524
A11: 7 | B11: Chewy Vites Greece (Vican) | C11: https://www.vican.gr/el/proionta.html?fylo=1223&manufacturer=1246 | D11: Open Ad Library | E11: Chewy Vites gummy vitamins for kids & adults (brand sold via pharmacies) | F11: Yes – gummies only | G11: Chewy Vites Kids Multivitamin Plus, 60 gummies (pharmacy price) | H11: 13.92 | I11: EUR | J11: =IF(H11="","",H11*INDEX(FX!$B$5:$B$11,MATCH(I11,FX!$A$5:$A$11,0))) -> 13.92 | K11: 15% off kids vitamin C gummies (in ads) | L11: 45910 | M11: =IF(L11="","",'Read me'!$B$3-L11) -> 390 | N11: 49 | O11: 11 | P11: 45911 | Q11: =IF(P11="","",'Read me'!$B$3-P11) -> 389 | R11: Brand site has no checkout (shows €0 / out of stock); price from a Greek online pharmacy (familypharmacy.gr).
A12: 8 | B12: Herbalist | C12: https://www.herbalist.gr | D12: Open Ad Library | E12: Herbal supplements (digestion, women's health – Gasdep, Erbofemin) | F12: No (capsules) | G12: Gasdep 45 capsules (advertised) | I12: EUR | J12: =IF(H12="","",H12*INDEX(FX!$B$5:$B$11,MATCH(I12,FX!$A$5:$A$11,0))) | K12: No price shown online – the site sends buyers to pharmacies/phone orders | L12: 46077 | M12: =IF(L12="","",'Read me'!$B$3-L12) -> 223 | N12: 6 | O12: 5 | P12: 46135 | Q12: =IF(P12="","",'Read me'!$B$3-P12) -> 165 | R12: No online prices on the brand site.

Sheet Slovenia
A1: Slovenia – stores selling gummies / supplements with Meta ads
A2: 7 stores · Meta data collected on the date in 'Read me'!B3 · sorted by number of ads
A4: # | B4: Store | C4: Store link | D4: Meta Ad Library link | E4: What they sell | F4: Sells gummies? | G4: Entry product | H4: Entry price (local) | I4: Currency | J4: Entry price (EUR) | K4: Offer | L4: Oldest ad in Ad Library (active or not) | M4: Days since oldest ad | N4: Ads in Ad Library (total) | O4: Active ads now | P4: Oldest live ad: start date | Q4: Days since oldest live ad | R4: Notes
A5: 1 | B5: Golden Tree Slovenija | C5: https://goldentree.si | D5: Open Ad Library | E5: Women's & men's supplement complexes, slimming (capsules/drinks) | F5: No | G5: Men's complex | H5: 39.9 | I5: EUR | J5: =IF(H5="","",H5*INDEX(FX!$B$5:$B$11,MATCH(I5,FX!$A$5:$A$11,0))) -> 39.9 | K5: 2nd product −50% (e.g. 2x Nighttime Burn −50%); free shipping for VIP Gold members | L5: 45572 | M5: =IF(L5="","",'Read me'!$B$3-L5) -> 728 | N5: 12015 | O5: 794 | P5: 46083 | Q5: =IF(P5="","",'Read me'!$B$3-P5) -> 217
A6: 2 | B6: Sensilab.si | C6: https://www.sensilab.si | D6: Open Ad Library | E6: Own-brand supplements (hormones, liver, joints, menopause), some gummies | F6: Some | G6: Hormone-balance capsules (bestseller) | H6: 24.99 | I6: EUR | J6: =IF(H6="","",H6*INDEX(FX!$B$5:$B$11,MATCH(I6,FX!$A$5:$A$11,0))) -> 24.99 | K6: −50% on 2-packs (e.g. 2x Curcuma Forte 24.99 €); up to −75%; free delivery over 49.99 € | L6: 45370 | M6: =IF(L6="","",'Read me'!$B$3-L6) -> 930 | N6: 2114 | O6: 177 | P6: 46128 | Q6: =IF(P6="","",'Read me'!$B$3-P6) -> 172
A7: 3 | B7: Malinca – Polna shramba zdravja | C7: https://www.malinca.si | D7: Open Ad Library | E7: Natural food, supplements & cosmetics, incl. kids gummies | F7: Yes (kids gummies) | G7: Kids multivitamin powder (offer) | H7: 11.98 | I7: EUR | J7: =IF(H7="","",H7*INDEX(FX!$B$5:$B$11,MATCH(I7,FX!$A$5:$A$11,0))) -> 11.98 | K7: "Today 40–50% off everything"; bundles; free shipping over 55 € | L7: 43941 | M7: =IF(L7="","",'Read me'!$B$3-L7) -> 2359 | N7: 2069 | O7: 115 | P7: 46155 | Q7: =IF(P7="","",'Read me'!$B$3-P7) -> 145
A8: 4 | B8: Medex | C8: https://www.medex.si | D8: Open Ad Library | E8: Royal jelly, magnesium, joint & kids supplements | F8: No (ampoules, powders, tablets) | I8: EUR | J8: =IF(H8="","",H8*INDEX(FX!$B$5:$B$11,MATCH(I8,FX!$A$5:$A$11,0))) | K8: Site blocked the scraper – open the link | L8: 45193 | M8: =IF(L8="","",'Read me'!$B$3-L8) -> 1107 | N8: 1954 | O8: 260 | P8: 46114 | Q8: =IF(P8="","",'Read me'!$B$3-P8) -> 186 | R8: Same company as Medex Hrvatska (2+1 / 3+1 free packs there). The Slovenian site blocked our scraper.
A9: 5 | B9: Bloom Robbins SI | C9: https://www.bloomrobbins.si | D9: Open Ad Library | E9: Hair gummies, ACV digestion gummies, hair bundles | F9: Yes – hero product | G9: ACV vitamins for digestion & energy, 1-month pack (advertised) | H9: 19.95 | I9: EUR | J9: =IF(H9="","",H9*INDEX(FX!$B$5:$B$11,MATCH(I9,FX!$A$5:$A$11,0))) -> 19.95 | K9: Hair bundles −31% / −35%; 30.00 → 19.95 € on ACV gummies; free delivery over 60 €; 90-day guarantee | L9: 45404 | M9: =IF(L9="","",'Read me'!$B$3-L9) -> 896 | N9: 1127 | O9: 187 | P9: 46092 | Q9: =IF(P9="","",'Read me'!$B$3-P9) -> 208
A10: 6 | B10: Valens | C10: https://valens.si | D10: Open Ad Library | E10: Slovenian supplements (amino, omega-3, Quvital) | F10: No | G10: Quvital 100 mg capsules | H10: 23.21 | I10: EUR | J10: =IF(H10="","",H10*INDEX(FX!$B$5:$B$11,MATCH(I10,FX!$A$5:$A$11,0))) -> 23.21 | K10: −20% when buying 4 of the same product (in ads); −10% markdowns (25.79 → 23.21 €) | L10: 45836 | M10: =IF(L10="","",'Read me'!$B$3-L10) -> 464 | N10: 289 | O10: 48 | P10: 46080 | Q10: =IF(P10="","",'Read me'!$B$3-P10) -> 220
A11: 7 | B11: LUNI GUMI | C11: https://lunigumi.si | D11: Open Ad Library | E11: Functional gummies (immunity, kids, sleep with melatonin + CBD) | F11: Yes – gummies only | G11: LUNI Lahko noč (sleep) gummies, 60 pcs | H11: 21.93 | I11: EUR | J11: =IF(H11="","",H11*INDEX(FX!$B$5:$B$11,MATCH(I11,FX!$A$5:$A$11,0))) -> 21.93 | K11: −10% (24.37 → 21.93 €); immunity gummies −20%; −10% newsletter code | L11: 45940 | M11: =IF(L11="","",'Read me'!$B$3-L11) -> 360 | N11: 66 | O11: 0 | Q11: =IF(P11="","",'Read me'!$B$3-P11) | R11: No active ads on the collection date (Meta returned none in repeated checks).

Sheet Slovakia
A1: Slovakia – stores selling gummies / supplements with Meta ads
A2: 6 stores · Meta data collected on the date in 'Read me'!B3 · sorted by number of ads
A4: # | B4: Store | C4: Store link | D4: Meta Ad Library link | E4: What they sell | F4: Sells gummies? | G4: Entry product | H4: Entry price (local) | I4: Currency | J4: Entry price (EUR) | K4: Offer | L4: Oldest ad in Ad Library (active or not) | M4: Days since oldest ad | N4: Ads in Ad Library (total) | O4: Active ads now | P4: Oldest live ad: start date | Q4: Days since oldest live ad | R4: Notes
A5: 1 | B5: Bloom Robbins SK/CZ | C5: https://www.bloomrobbins.sk | D5: Open Ad Library | E5: Hair-growth gummies ("Love is in the Hair"), collagen, hair serums & sprays | F5: Yes – hero product | G5: Love is in the Hair gummies, 1 pack | H5: 29.95 | I5: EUR | J5: =IF(H5="","",H5*INDEX(FX!$B$5:$B$11,MATCH(I5,FX!$A$5:$A$11,0))) -> 29.95 | K5: Bundles; 90-day money-back guarantee; free shipping over 60 € | L5: 45593 | M5: =IF(L5="","",'Read me'!$B$3-L5) -> 707 | N5: 5905 | O5: 312 | P5: 46148 | Q5: =IF(P5="","",'Read me'!$B$3-P5) -> 152 | R5: Same Facebook page as Bloom Robbins CZ.
A6: 2 | B6: GymBeam | C6: https://gymbeam.sk | D6: Open Ad Library | E6: Sports nutrition & supplements (incl. "Yummies" gummies: multivitamin, creatine, zinc, D3…) | F6: Yes (Yummies line) | G6: Multivitamin Yummies, 60 gummies | H6: 7.5 | I6: EUR | J6: =IF(H6="","",H6*INDEX(FX!$B$5:$B$11,MATCH(I6,FX!$A$5:$A$11,0))) -> 7.5 | K6: Up to −25%; −20% on BeastPink with code PINK; free shipping over 60 € | L6: 45861 | M6: =IF(L6="","",'Read me'!$B$3-L6) -> 439 | N6: 3387 | O6: 192 | P6: 46022 | Q6: =IF(P6="","",'Read me'!$B$3-P6) -> 278
A7: 3 | B7: Protein a Co. | C7: https://www.proteinaco.sk | D7: Open Ad Library | E7: Own-brand protein, creatine, bars, vitamins, gummies | F7: Yes (gummies category) | G7: Capsule supplement (from) | H7: 5.84 | I7: EUR | J7: =IF(H7="","",H7*INDEX(FX!$B$5:$B$11,MATCH(I7,FX!$A$5:$A$11,0))) -> 5.84 | K7: Up to −56%; 5+1 free on bars; 2+1 free on SNACK IT protein; free shipping over 99 € | L7: 45405 | M7: =IF(L7="","",'Read me'!$B$3-L7) -> 895 | N7: 1562 | O7: 168 | P7: 45588 | Q7: =IF(P7="","",'Read me'!$B$3-P7) -> 712
A8: 4 | B8: Zdravý svet | C8: https://www.zdravysvet.sk | D8: Open Ad Library | E8: Herbal e-shop: Vesantech supplements, tinctures, mushrooms, probiotics | F8: No (capsules/liquids) | G8: Vesantech HAIR vitamins booster (advertised) | H8: 32 | I8: EUR | J8: =IF(H8="","",H8*INDEX(FX!$B$5:$B$11,MATCH(I8,FX!$A$5:$A$11,0))) -> 32 | K8: Build-a-bundle up to −20% + free gift; 2+1 on Vesantech probiotics; free shipping over 70 € | L8: 45730 | M8: =IF(L8="","",'Read me'!$B$3-L8) -> 570 | N8: 786 | O8: 278 | P8: 45860 | Q8: =IF(P8="","",'Read me'!$B$3-P8) -> 440
A9: 5 | B9: FutuNatura - Môj život | C9: https://www.futunatura.sk | D9: Open Ad Library | E9: Own-brand supplements incl. gummies (hair/skin/nails, kids, creatine) | F9: Yes (part of range) | G9: Hair, Skin & Nails gummies, 120 pcs (advertised) | H9: 14.99 | I9: EUR | J9: =IF(H9="","",H9*INDEX(FX!$B$5:$B$11,MATCH(I9,FX!$A$5:$A$11,0))) -> 14.99 | K9: Weekly offer −15% on everything (19.99 → 14.99 €); quantity discount; free shipping over 35 €; gift over 50–100 € | L9: 45569 | M9: =IF(L9="","",'Read me'!$B$3-L9) -> 731 | N9: 122 | O9: 25 | P9: 45572 | Q9: =IF(P9="","",'Read me'!$B$3-P9) -> 728
A10: 6 | B10: TummyTox Slovenská republika | C10: https://www.tummytox.sk | D10: Open Ad Library | E10: Women's weight-loss & beauty supplements: teas, gummies, bundles | F10: Yes (multivitamin gummies) | G10: Multivitamin Gummies 3-pack (180 days) | H10: 34.99 | I10: EUR | J10: =IF(H10="","",H10*INDEX(FX!$B$5:$B$11,MATCH(I10,FX!$A$5:$A$11,0))) -> 34.99 | K10: −53% on the 3-pack (74.97 → 34.99 €); free shipping over 40 €; free gift over 50 €; −10% first order | L10: 45349 | M10: =IF(L10="","",'Read me'!$B$3-L10) -> 951 | N10: 47 | O10: 6 | P10: 45351 | Q10: =IF(P10="","",'Read me'!$B$3-P10) -> 949

Sheet Croatia
A1: Croatia – stores selling gummies / supplements with Meta ads
A2: 8 stores · Meta data collected on the date in 'Read me'!B3 · sorted by number of ads
A4: # | B4: Store | C4: Store link | D4: Meta Ad Library link | E4: What they sell | F4: Sells gummies? | G4: Entry product | H4: Entry price (local) | I4: Currency | J4: Entry price (EUR) | K4: Offer | L4: Oldest ad in Ad Library (active or not) | M4: Days since oldest ad | N4: Ads in Ad Library (total) | O4: Active ads now | P4: Oldest live ad: start date | Q4: Days since oldest live ad | R4: Notes
A5: 1 | B5: Carnium Botanicals Hrvatska | C5: https://zdravlje.carniumbotanicals.hr | D5: Open Ad Library | E5: Herbal capsules for women's health, digestion (Bloat Aid, Her Biotic), menopause | F5: No (capsules) | G5: Women's herbal capsules (from) | H5: 26.9 | I5: EUR | J5: =IF(H5="","",H5*INDEX(FX!$B$5:$B$11,MATCH(I5,FX!$A$5:$A$11,0))) -> 26.9 | K5: Code ŽENA20 −20% over 50 €; bundles −10% / −20%; free e-book; free delivery over 40–50 €; cash on delivery | L5: 45592 | M5: =IF(L5="","",'Read me'!$B$3-L5) -> 708 | N5: 6109 | O5: 247 | P5: 46085 | Q5: =IF(P5="","",'Read me'!$B$3-P5) -> 215
A6: 2 | B6: SenseFit Brand | C6: https://sensefit.shop | D6: Open Ad Library | E6: Shilajit and other supplements | F6: No (resin/capsules) | G6: Shilajit (advertised) | H6: 27.97 | I6: EUR | J6: =IF(H6="","",H6*INDEX(FX!$B$5:$B$11,MATCH(I6,FX!$A$5:$A$11,0))) -> 27.97 | K6: 2 + 1 FREE (buy 2 boxes, 1 free); price cut 37.97 → 27.97 € | L6: 45847 | M6: =IF(L6="","",'Read me'!$B$3-L6) -> 453 | N6: 3985 | O6: 321 | P6: 45892 | Q6: =IF(P6="","",'Read me'!$B$3-P6) -> 408
A7: 3 | B7: Medex Hrvatska | C7: https://www.medexlife.hr | D7: Open Ad Library | E7: Royal jelly, magnesium, kids supplements (Slovenian brand) | F7: No (ampoules, powders, tablets) | G7: Gelée Royale Junior (advertised) | H7: 17.69 | I7: EUR | J7: =IF(H7="","",H7*INDEX(FX!$B$5:$B$11,MATCH(I7,FX!$A$5:$A$11,0))) -> 17.69 | K7: 2+1 FREE on Gelée Royale packs; 3+1 FREE on Magnesium packs; up to −33% | L7: 45212 | M7: =IF(L7="","",'Read me'!$B$3-L7) -> 1088 | N7: 2251 | O7: 357 | P7: 46114 | Q7: =IF(P7="","",'Read me'!$B$3-P7) -> 186
A8: 4 | B8: Sensilab.hr | C8: https://www.sensilab.hr | D8: Open Ad Library | E8: Own-brand supplements (hormones, thyroid, liver, menopause), some gummies | F8: Some | G8: Milk-thistle capsules (bestseller) | H8: 18.99 | I8: EUR | J8: =IF(H8="","",H8*INDEX(FX!$B$5:$B$11,MATCH(I8,FX!$A$5:$A$11,0))) -> 18.99 | K8: Bestsellers up to −58% (35.99 → 18.99 €); free delivery over 35 € | L8: 45433 | M8: =IF(L8="","",'Read me'!$B$3-L8) -> 867 | N8: 1940 | O8: 159 | P8: 46104 | Q8: =IF(P8="","",'Read me'!$B$3-P8) -> 196
A9: 5 | B9: Malinca | C9: https://www.malinca.hr | D9: Open Ad Library | E9: Natural food, supplements & cosmetics shop, incl. kids gummies | F9: Yes (kids gummies) | G9: Omega-3 gummies for kids (advertised) | H9: 13.78 | I9: EUR | J9: =IF(H9="","",H9*INDEX(FX!$B$5:$B$11,MATCH(I9,FX!$A$5:$A$11,0))) -> 13.78 | K9: "Today 40–50% off everything"; bundles; free delivery over 55 € | L9: 45155 | M9: =IF(L9="","",'Read me'!$B$3-L9) -> 1145 | N9: 1043 | O9: 40 | P9: 46155 | Q9: =IF(P9="","",'Read me'!$B$3-P9) -> 145
A10: 6 | B10: Redo Gummies | C10: https://redogummies.com | D10: Open Ad Library | E10: Hair, Skin & Nails vitamin gummies (single-product brand) | F10: Yes – gummies only | G10: REDO Hair, Skin & Nails gummies, 60 pcs (1 month) | H10: 2190 | I10: RSD | J10: =IF(H10="","",H10*INDEX(FX!$B$5:$B$11,MATCH(I10,FX!$A$5:$A$11,0))) -> 18.6807 | K10: No bundle shown on the product page | L10: 45966 | M10: =IF(L10="","",'Read me'!$B$3-L10) -> 334 | N10: 507 | O10: 177 | P10: 46260 | Q10: =IF(P10="","",'Read me'!$B$3-P10) -> 40 | R10: Store prices are in Serbian dinars (RSD) – a Serbian brand that also targets Croatia with ads.
A11: 7 | B11: FutuNatura - Moj život | C11: https://www.futunatura.hr | D11: Open Ad Library | E11: Own-brand supplements incl. kids gummies | F11: Yes (part of range) | G11: TUMMY probiotic gummies for kids, 30 pcs (advertised) | H11: 11.99 | I11: EUR | J11: =IF(H11="","",H11*INDEX(FX!$B$5:$B$11,MATCH(I11,FX!$A$5:$A$11,0))) -> 11.99 | K11: Weekly offer −15% on everything; quantity discount; free delivery over 39.99 €; free gift over 50 € | L11: 45595 | M11: =IF(L11="","",'Read me'!$B$3-L11) -> 705 | N11: 139 | O11: 74 | P11: 45595 | Q11: =IF(P11="","",'Read me'!$B$3-P11) -> 705
A12: 8 | B12: Vitamincic | C12: https://vitamincic.com | D12: Open Ad Library | E12: Liquid supplements: joint support, collagen, magnesium | F12: No (liquids) | G12: Magnesium glycinate 500 ml | H12: 23.9 | I12: EUR | J12: =IF(H12="","",H12*INDEX(FX!$B$5:$B$11,MATCH(I12,FX!$A$5:$A$11,0))) -> 23.9 | K12: Markdowns −10% to −30% (e.g. Joint Support MAX 38.90 → 28.90 €); 10% off popup | L12: 45631 | M12: =IF(L12="","",'Read me'!$B$3-L12) -> 669 | N12: 80 | O12: 3 | P12: 46256 | Q12: =IF(P12="","",'Read me'!$B$3-P12) -> 44

Sheet Czechia
A1: Czechia – stores selling gummies / supplements with Meta ads
A2: 8 stores · Meta data collected on the date in 'Read me'!B3 · sorted by number of ads
A4: # | B4: Store | C4: Store link | D4: Meta Ad Library link | E4: What they sell | F4: Sells gummies? | G4: Entry product | H4: Entry price (local) | I4: Currency | J4: Entry price (EUR) | K4: Offer | L4: Oldest ad in Ad Library (active or not) | M4: Days since oldest ad | N4: Ads in Ad Library (total) | O4: Active ads now | P4: Oldest live ad: start date | Q4: Days since oldest live ad | R4: Notes
A5: 1 | B5: Bloom Robbins SK/CZ | C5: https://www.bloomrobbins.cz | D5: Open Ad Library | E5: Hair-growth gummies ("Love is in the Hair"), collagen, hair serums & sprays | F5: Yes – hero product | G5: Love is in the Hair gummies, 1 pack | H5: 699 | I5: CZK | J5: =IF(H5="","",H5*INDEX(FX!$B$5:$B$11,MATCH(I5,FX!$A$5:$A$11,0))) -> 28.3095 | K5: Bundles; 90-day money-back guarantee; free shipping over 1,500 Kč | L5: 45593 | M5: =IF(L5="","",'Read me'!$B$3-L5) -> 707 | N5: 5905 | O5: 312 | P5: 46148 | Q5: =IF(P5="","",'Read me'!$B$3-P5) -> 152 | R5: Same Facebook page as Bloom Robbins SK.
A6: 2 | B6: Venira | C6: https://www.venira.cz | D6: Open Ad Library | E6: Natural cosmetics + supplements (hair/skin/nails capsules, slimming) | F6: No (capsules) | G6: Hair, skin & nails capsules – 40-day course, 80 caps | H6: 594 | I6: CZK | J6: =IF(H6="","",H6*INDEX(FX!$B$5:$B$11,MATCH(I6,FX!$A$5:$A$11,0))) -> 24.057 | K6: Price cut 699 → 594 Kč; free shipping; short-expiry clearance | L6: 45196 | M6: =IF(L6="","",'Read me'!$B$3-L6) -> 1104 | N6: 5678 | O6: 355 | P6: 46072 | Q6: =IF(P6="","",'Read me'!$B$3-P6) -> 228
A7: 3 | B7: Dafit.cz | C7: https://www.dafit.cz | D7: Open Ad Library | E7: Sports nutrition shop (multi-brand), incl. creatine gummies | F7: Some (creatine gummies) | G7: Cheapest item on homepage | H7: 17.12 | I7: EUR | J7: =IF(H7="","",H7*INDEX(FX!$B$5:$B$11,MATCH(I7,FX!$A$5:$A$11,0))) -> 17.12 | K7: Weekly promotions: 1+1 on ATP Creamelky creatine gummies, 1+1 on citrulline, free protein with whey | L7: 45596 | M7: =IF(L7="","",'Read me'!$B$3-L7) -> 704 | N7: 3292 | O7: 54 | P7: 46134 | Q7: =IF(P7="","",'Read me'!$B$3-P7) -> 166 | R7: Site shows EUR to non-CZ visitors; CZK prices on the CZ site. Oldest live ad: Meta throttled the lookup, true date may be earlier.
A8: 4 | B8: Flownutrition CZ | C8: https://flow-nutrition.cz | D8: Open Ad Library | E8: Premium own-made supplements (magnesium, daily essentials, beauty, creatine) | F8: No (capsules/powders) | G8: D3 + K2 vegan oil | H8: 199 | I8: CZK | J8: =IF(H8="","",H8*INDEX(FX!$B$5:$B$11,MATCH(I8,FX!$A$5:$A$11,0))) -> 8.0595 | K8: Free zinc with orders over 1,700 Kč; bundles up to −30% | L8: 45567 | M8: =IF(L8="","",'Read me'!$B$3-L8) -> 733 | N8: 925 | O8: 85 | P8: 46118 | Q8: =IF(P8="","",'Read me'!$B$3-P8) -> 182
A9: 5 | B9: Herbyway | C9: https://www.herbyway.cz | D9: Open Ad Library | E9: Czech supplements: magnesium, milk thistle, ashwagandha | F9: No (capsules/drinks) | G9: Magnesium bisglycinate 1900 mg | H9: 389 | I9: CZK | J9: =IF(H9="","",H9*INDEX(FX!$B$5:$B$11,MATCH(I9,FX!$A$5:$A$11,0))) -> 15.7545 | K9: Magnesium Drink 2+1 FREE; 1+1 promos; milk-thistle bundle; free shipping | L9: 46147 | M9: =IF(L9="","",'Read me'!$B$3-L9) -> 153 | N9: 833 | O9: 92 | P9: 46202 | Q9: =IF(P9="","",'Read me'!$B$3-P9) -> 98
A10: 6 | B10: ADVANCE nutraceutics | C10: https://www.nutraceutics.cz | D10: Open Ad Library | E10: Czech-made capsules: probiotics, cholesterol, testosterone, sugar control | F10: No (capsules) | G10: Probio24 60 capsules | H10: 309 | I10: CZK | J10: =IF(H10="","",H10*INDEX(FX!$B$5:$B$11,MATCH(I10,FX!$A$5:$A$11,0))) -> 12.5145 | K10: ADVANCE DAYS: −50 Kč per item with code ADVANCE (359 → 309 Kč); free shipping with 3 items | L10: 45366 | M10: =IF(L10="","",'Read me'!$B$3-L10) -> 934 | N10: 743 | O10: 131 | P10: 45953 | Q10: =IF(P10="","",'Read me'!$B$3-P10) -> 347
A11: 7 | B11: GUMMYLIFE.cz | C11: https://www.gummylife.cz | D11: Open Ad Library | E11: CBD gummies (sleep, stress, pain) | F11: Yes – gummies only | G11: CBD Na Noc – ½ pack (advertised sleep page) | H11: 820 | I11: CZK | J11: =IF(H11="","",H11*INDEX(FX!$B$5:$B$11,MATCH(I11,FX!$A$5:$A$11,0))) -> 33.21 | K11: "Balíček 3 v 1" bundle on sale; free shipping over 2,700 Kč; ships in 24 h | L11: 45827 | M11: =IF(L11="","",'Read me'!$B$3-L11) -> 473 | N11: 709 | O11: 43 | P11: 46169 | Q11: =IF(P11="","",'Read me'!$B$3-P11) -> 131
A12: 8 | B12: Puravia | C12: https://www.puravia.cz | D12: Open Ad Library | E12: Clean-label supplements incl. MycoGummies (mushroom gummies) | F12: Yes (MycoGummies) | G12: MycoGummies – mushroom gummies, 60 pcs | H12: 390 | I12: CZK | J12: =IF(H12="","",H12*INDEX(FX!$B$5:$B$11,MATCH(I12,FX!$A$5:$A$11,0))) -> 15.795 | K12: Up to −15% on Garden of Life; gifts from 999 Kč (4 tiers); free shipping over 2,000 Kč | L12: 45118 | M12: =IF(L12="","",'Read me'!$B$3-L12) -> 1182 | N12: 499 | O12: 10 | P12: 46135 | Q12: =IF(P12="","",'Read me'!$B$3-P12) -> 165

Sheet Hungary
A1: Hungary – stores selling gummies / supplements with Meta ads
A2: 8 stores · Meta data collected on the date in 'Read me'!B3 · sorted by number of ads
A4: # | B4: Store | C4: Store link | D4: Meta Ad Library link | E4: What they sell | F4: Sells gummies? | G4: Entry product | H4: Entry price (local) | I4: Currency | J4: Entry price (EUR) | K4: Offer | L4: Oldest ad in Ad Library (active or not) | M4: Days since oldest ad | N4: Ads in Ad Library (total) | O4: Active ads now | P4: Oldest live ad: start date | Q4: Days since oldest live ad | R4: Notes
A5: 1 | B5: Obstermann's (termeszetesgumicukor.hu) | C5: https://termeszetesgumicukor.hu | D5: Open Ad Library | E5: Natural apple-based gummy vitamins (multivitamin, ACV, kids) | F5: Yes – gummies only | G5: "Four wishes" bundle – 4 products of choice | H5: 13970 | I5: HUF | J5: =IF(H5="","",H5*INDEX(FX!$B$5:$B$11,MATCH(I5,FX!$A$5:$A$11,0))) -> 35.6235 | K5: −46% on the 4-product bundle (25,940 → 13,970 Ft); bigger bundle = bigger saving; 1,000 Ft coupon on first order | L5: 45189 | M5: =IF(L5="","",'Read me'!$B$3-L5) -> 1111 | N5: 905 | O5: 181 | P5: 46141 | Q5: =IF(P5="","",'Read me'!$B$3-P5) -> 159
A6: 2 | B6: Hairburst Hungary | C6: https://www.hairburst.com/hu-hu | D6: Open Ad Library | E6: Hair-growth gummies, shampoos, elixirs (UK brand, HU page) | F6: Yes | G6: Hajnövesztő Gumivitamin (hair gummies) | H6: 10630 | I6: HUF | J6: =IF(H6="","",H6*INDEX(FX!$B$5:$B$11,MATCH(I6,FX!$A$5:$A$11,0))) -> 27.1065 | K6: 1+1 FREE (buy one get one free, limited time) | L6: 45856 | M6: =IF(L6="","",'Read me'!$B$3-L6) -> 444 | N6: 876 | O6: 70 | P6: 46246 | Q6: =IF(P6="","",'Read me'!$B$3-P6) -> 54
A7: 3 | B7: Shilami (shilajitgumivitamin.hu) | C7: https://shilajitgumivitamin.hu | D7: Open Ad Library | E7: Shilajit gummies (men's and women's) | F7: Yes – gummies only | G7: Női (women's) Shilajit gummies, 30 days | H7: 8990 | I7: HUF | J7: =IF(H7="","",H7*INDEX(FX!$B$5:$B$11,MATCH(I7,FX!$A$5:$A$11,0))) -> 22.9245 | K7: Women's version on sale 11,890 → 8,990 Ft; men's 11,890 Ft | L7: 46227 | M7: =IF(L7="","",'Read me'!$B$3-L7) -> 73 | N7: 319 | O7: 117 | P7: 46267 | Q7: =IF(P7="","",'Read me'!$B$3-P7) -> 33
A8: 4 | B8: Queen's Ritual | C8: https://queensritual.hu | D8: Open Ad Library | E8: Intimate-health gummies for women | F8: Yes – gummies only | G8: 1 pack – 1-month course, 60 pcs | H8: 9990 | I8: HUF | J8: =IF(H8="","",H8*INDEX(FX!$B$5:$B$11,MATCH(I8,FX!$A$5:$A$11,0))) -> 25.4745 | K8: 1+1 FREE + free shipping (5,995 Ft/pack); 2+2 FREE (4,997 Ft/pack); "only 47 packs left at this price" | L8: 46204 | M8: =IF(L8="","",'Read me'!$B$3-L8) -> 96 | N8: 281 | O8: 45 | P8: 46279 | Q8: =IF(P8="","",'Read me'!$B$3-P8) -> 21
A9: 5 | B9: Magic Hair HU | C9: https://magichair.hu | D9: Open Ad Library | E9: Hair gummies (Keratin Bomb), hair tools, collagen products | F9: Yes | G9: Bundle (advertised) | H9: 6500 | I9: HUF | J9: =IF(H9="","",H9*INDEX(FX!$B$5:$B$11,MATCH(I9,FX!$A$5:$A$11,0))) -> 16.575 | K9: Bundles at 50% off (13,000 → 6,500 Ft); "Halloween doubling"; free shipping over 20,000 Ft | L9: 45682 | M9: =IF(L9="","",'Read me'!$B$3-L9) -> 618 | N9: 210 | O9: 10 | P9: 46157 | Q9: =IF(P9="","",'Read me'!$B$3-P9) -> 143
A10: 6 | B10: Marslakócskák | C10: https://www.marslakocskak.hu | D10: Open Ad Library | E10: Kids multivitamins: gummies, chewables, syrups | F10: Yes (kids gummies) | I10: HUF | J10: =IF(H10="","",H10*INDEX(FX!$B$5:$B$11,MATCH(I10,FX!$A$5:$A$11,0))) | K10: Prices not shown on the website (sold in pharmacies) | L10: 45922 | M10: =IF(L10="","",'Read me'!$B$3-L10) -> 378 | N10: 192 | O10: 2 | P10: 46294 | Q10: =IF(P10="","",'Read me'!$B$3-P10) -> 6 | R10: Brand sold through pharmacies; no prices on its own site.
A11: 7 | B11: Vitaful Magyarország | C11: https://vitaful.hu | D11: Open Ad Library | E11: Vegan gummy vitamins for adults & kids | F11: Yes – gummies only | G11: Hair gummies (Hajszépítő Gumivitamin) | H11: 8459 | I11: HUF | J11: =IF(H11="","",H11*INDEX(FX!$B$5:$B$11,MATCH(I11,FX!$A$5:$A$11,0))) -> 21.57045 | K11: −15% / −20% markdowns (9,950 → 8,459 Ft); 1+1 promos; free delivery over 15,000 Ft | L11: 45925 | M11: =IF(L11="","",'Read me'!$B$3-L11) -> 375 | N11: 49 | O11: 2 | P11: 46283 | Q11: =IF(P11="","",'Read me'!$B$3-P11) -> 17
A12: 8 | B12: Bioextra | C12: https://bioextra.hu | D12: Open Ad Library | E12: Hungarian vitamin & supplement brand (capsules, tablets) | F12: No | G12: Bioextra C+D Forte retard, 100 caps (offer) | H12: 990 | I12: HUF | J12: =IF(H12="","",H12*INDEX(FX!$B$5:$B$11,MATCH(I12,FX!$A$5:$A$11,0))) -> 2.5245 | K12: "Only 990 Ft" deal on C+D Forte; free shipping over 10,000 Ft | L12: 44673 | M12: =IF(L12="","",'Read me'!$B$3-L12) -> 1627 | N12: 30 | O12: 4 | P12: 45568 | Q12: =IF(P12="","",'Read me'!$B$3-P12) -> 732
