Workbook

Sheet Read me
A1: Gummy & supplement stores – Meta ads tracker
A3: Data collected on | B3: 46300
A4: Countries | B4: France, Germany, Italy, Belgium, Netherlands, Spain, Portugal, Switzerland, Ireland, Austria (one tab each)
A6: COLUMNS
A7: Store link | B7: The store website (where the ads send people).
A8: Meta Ad Library link | B8: Opens the store's Facebook page in Meta Ad Library (all countries, active + inactive ads). Use it to re-check every number.
A9: Entry price | B9: Lowest price to buy ONE unit of the main product the store advertises (after the discount shown on the site). Local currency; the EUR column converts it with the FX tab.
A10: Offer | B10: The promotion shown on the store / ad landing page at collection time (bundles like 2+1, % off, free shipping threshold, gifts).
A11: Oldest ad in Ad Library | B11: Start date of the oldest ad Meta Ad Library still shows for the page, active or inactive. Best available proxy for when they started advertising.
A12: Ads in Ad Library | B12: Number of ads Meta shows for the page (all countries, active + inactive). Meta rounds big numbers.
A13: Active ads now | B13: Ads running on the collection date.
A14: Oldest live ad: start date | B14: Start date of the longest-running ad that is still active. An ad running for a long time is usually a proven winner.
A15: Days since … | B15: Formulas: Data collected on (cell B3) minus the date. Change B3 to TODAY() if you want them to keep counting.
A17: LIMITATIONS
A18: Ad retention | B18: Meta keeps inactive ads that ran in the EU for about 1 year after they stop (DSA rule). Stores advertising longer than that may have started earlier than 'Oldest ad in Ad Library' shows.
A19: Switzerland | B19: Switzerland is not in the EU: ads that ran only there disappear from the Ad Library once they stop. For Swiss-only advertisers the oldest-ad date mostly reflects ads that are still running.
A20: Page vs. store | B20: Counts are per Facebook page, across all countries. Several brands run one page for many countries (e.g. ESN, Lashilé, Bears with Benefits DE/AT), so their numbers include ads outside the tab's country.
A21: Prices | B21: Collected from the store websites on the collection date. Promotions change often.
A22: Selection | B22: Stores were found by searching active Meta ads in each country for local words for gummies and food supplements, plus web searches. It is a list of active advertisers, not a full census.
A23: Blank cell | B23: The value could not be collected (site blocked the scraper, or Meta throttled the lookup). Open the link to check.
A25: COLOUR LEGEND
A26: Blue text | B26: Numbers collected from websites / Meta Ad Library.
A27: Black text | B27: Formulas – do not overwrite.
A28: Yellow cells | B28: Inputs you can edit (collection date, FX rates).

Sheet FX
A1: Exchange rates used for EUR conversion
A2: Approximate rates (assumption, Oct 2026). Edit the yellow cells and every EUR column recalculates.
A4: Currency | B4: EUR per 1 unit
A5: EUR | B5: 1
A6: CHF | B6: 1.07
A7: GBP | B7: 1.17
A8: USD | B8: 0.92

Sheet Summary
A1: Summary by country
A3: Country | B3: Stores listed | C3: Stores selling gummies ("Yes…") | D3: Total ads (all stores) | E3: Active ads now (all stores) | F3: Median entry price (EUR) | G3: Store with most ads | H3: Earliest oldest ad
A4: France | B4: =COUNTA(France!$B$5:$B$12) -> 8 | C4: =COUNTIF(France!$F$5:$F$12,"Yes*") -> 4 | D4: =SUM(France!$N$5:$N$12) -> 15657 | E4: =SUM(France!$O$5:$O$12) -> 2445 | F4: =IFERROR(MEDIAN(France!$J$5:$J$12),"") -> 32.45 | G4: =INDEX(France!$B$5:$B$12,MATCH(MAX(France!$N$5:$N$12),France!$N$5:$N$12,0)) -> French Mush | H4: =IF(COUNT(France!$L$5:$L$12)=0,"",MIN(France!$L$5:$L$12)) -> 44628
A5: Germany | B5: =COUNTA(Germany!$B$5:$B$12) -> 8 | C5: =COUNTIF(Germany!$F$5:$F$12,"Yes*") -> 5 | D5: =SUM(Germany!$N$5:$N$12) -> 28086 | E5: =SUM(Germany!$O$5:$O$12) -> 4450 | F5: =IFERROR(MEDIAN(Germany!$J$5:$J$12),"") -> 23.9 | G5: =INDEX(Germany!$B$5:$B$12,MATCH(MAX(Germany!$N$5:$N$12),Germany!$N$5:$N$12,0)) -> ahead | H5: =IF(COUNT(Germany!$L$5:$L$12)=0,"",MIN(Germany!$L$5:$L$12)) -> 44166
A6: Italy | B6: =COUNTA(Italy!$B$5:$B$13) -> 9 | C6: =COUNTIF(Italy!$F$5:$F$13,"Yes*") -> 3 | D6: =SUM(Italy!$N$5:$N$13) -> 9274 | E6: =SUM(Italy!$O$5:$O$13) -> 1027 | F6: =IFERROR(MEDIAN(Italy!$J$5:$J$13),"") -> 19.99 | G6: =INDEX(Italy!$B$5:$B$13,MATCH(MAX(Italy!$N$5:$N$13),Italy!$N$5:$N$13,0)) -> Sensilab.it | H6: =IF(COUNT(Italy!$L$5:$L$13)=0,"",MIN(Italy!$L$5:$L$13)) -> 45432
A7: Belgium | B7: =COUNTA(Belgium!$B$5:$B$12) -> 8 | C7: =COUNTIF(Belgium!$F$5:$F$12,"Yes*") -> 6 | D7: =SUM(Belgium!$N$5:$N$12) -> 10443 | E7: =SUM(Belgium!$O$5:$O$12) -> 1305 | F7: =IFERROR(MEDIAN(Belgium!$J$5:$J$12),"") -> 34.7 | G7: =INDEX(Belgium!$B$5:$B$12,MATCH(MAX(Belgium!$N$5:$N$12),Belgium!$N$5:$N$12,0)) -> Kruidvat België/Belgique | H7: =IF(COUNT(Belgium!$L$5:$L$12)=0,"",MIN(Belgium!$L$5:$L$12)) -> 45036
A8: Netherlands | B8: =COUNTA(Netherlands!$B$5:$B$13) -> 9 | C8: =COUNTIF(Netherlands!$F$5:$F$13,"Yes*") -> 5 | D8: =SUM(Netherlands!$N$5:$N$13) -> 13367 | E8: =SUM(Netherlands!$O$5:$O$13) -> 2170 | F8: =IFERROR(MEDIAN(Netherlands!$J$5:$J$13),"") -> 24.95 | G8: =INDEX(Netherlands!$B$5:$B$13,MATCH(MAX(Netherlands!$N$5:$N$13),Netherlands!$N$5:$N$13,0)) -> WeightWorld | H8: =IF(COUNT(Netherlands!$L$5:$L$13)=0,"",MIN(Netherlands!$L$5:$L$13)) -> 45293
A9: Spain | B9: =COUNTA(Spain!$B$5:$B$13) -> 9 | C9: =COUNTIF(Spain!$F$5:$F$13,"Yes*") -> 5 | D9: =SUM(Spain!$N$5:$N$13) -> 8489 | E9: =SUM(Spain!$O$5:$O$13) -> 1551 | F9: =IFERROR(MEDIAN(Spain!$J$5:$J$13),"") -> 29.9 | G9: =INDEX(Spain!$B$5:$B$13,MATCH(MAX(Spain!$N$5:$N$13),Spain!$N$5:$N$13,0)) -> Aldous Bio | H9: =IF(COUNT(Spain!$L$5:$L$13)=0,"",MIN(Spain!$L$5:$L$13)) -> 44008
A10: Portugal | B10: =COUNTA(Portugal!$B$5:$B$13) -> 9 | C10: =COUNTIF(Portugal!$F$5:$F$13,"Yes*") -> 2 | D10: =SUM(Portugal!$N$5:$N$13) -> 3703 | E10: =SUM(Portugal!$O$5:$O$13) -> 500 | F10: =IFERROR(MEDIAN(Portugal!$J$5:$J$13),"") -> 18.78 | G10: =INDEX(Portugal!$B$5:$B$13,MATCH(MAX(Portugal!$N$5:$N$13),Portugal!$N$5:$N$13,0)) -> Sensilab.pt | H10: =IF(COUNT(Portugal!$L$5:$L$13)=0,"",MIN(Portugal!$L$5:$L$13)) -> 45208
A11: Switzerland | B11: =COUNTA(Switzerland!$B$5:$B$16) -> 12 | C11: =COUNTIF(Switzerland!$F$5:$F$16,"Yes*") -> 1 | D11: =SUM(Switzerland!$N$5:$N$16) -> 9507 | E11: =SUM(Switzerland!$O$5:$O$16) -> 2579 | F11: =IFERROR(MEDIAN(Switzerland!$J$5:$J$16),"") -> 29.16285 | G11: =INDEX(Switzerland!$B$5:$B$16,MATCH(MAX(Switzerland!$N$5:$N$16),Switzerland!$N$5:$N$16,0)) -> Lynae | H11: =IF(COUNT(Switzerland!$L$5:$L$16)=0,"",MIN(Switzerland!$L$5:$L$16)) -> 45190
A12: Ireland | B12: =COUNTA(Ireland!$B$5:$B$12) -> 8 | C12: =COUNTIF(Ireland!$F$5:$F$12,"Yes*") -> 5 | D12: =SUM(Ireland!$N$5:$N$12) -> 10439 | E12: =SUM(Ireland!$O$5:$O$12) -> 1370 | F12: =IFERROR(MEDIAN(Ireland!$J$5:$J$12),"") -> 34.94 | G12: =INDEX(Ireland!$B$5:$B$12,MATCH(MAX(Ireland!$N$5:$N$12),Ireland!$N$5:$N$12,0)) -> Novomins Nutrition | H12: =IF(COUNT(Ireland!$L$5:$L$12)=0,"",MIN(Ireland!$L$5:$L$12)) -> 44923
A13: Austria | B13: =COUNTA(Austria!$B$5:$B$13) -> 9 | C13: =COUNTIF(Austria!$F$5:$F$13,"Yes*") -> 2 | D13: =SUM(Austria!$N$5:$N$13) -> 8580 | E13: =SUM(Austria!$O$5:$O$13) -> 1356 | F13: =IFERROR(MEDIAN(Austria!$J$5:$J$13),"") -> 29 | G13: =INDEX(Austria!$B$5:$B$13,MATCH(MAX(Austria!$N$5:$N$13),Austria!$N$5:$N$13,0)) -> Bears with Benefits | H13: =IF(COUNT(Austria!$L$5:$L$13)=0,"",MIN(Austria!$L$5:$L$13)) -> 44166

Sheet France
A1: France – stores selling gummies / supplements with Meta ads
A2: 8 stores · Meta data collected on the date in 'Read me'!B3 · sorted by number of ads
A4: # | B4: Store | C4: Store link | D4: Meta Ad Library link | E4: What they sell | F4: Sells gummies? | G4: Entry product | H4: Entry price (local) | I4: Currency | J4: Entry price (EUR) | K4: Offer | L4: Oldest ad in Ad Library (active or not) | M4: Days since oldest ad | N4: Ads in Ad Library (total) | O4: Active ads now | P4: Oldest live ad: start date | Q4: Days since oldest live ad | R4: Notes
A5: 1 | B5: French Mush | C5: https://www.frenchmush.com | D5: Open Ad Library | E5: Functional mushroom supplements (capsules, coffee alternative) | F5: No (capsules/powders) | G5: Boost coffee alternative (one-time, ~30 days) | H5: 29.9 | I5: EUR | J5: =IF(H5="","",H5*INDEX(FX!$B$5:$B$8,MATCH(I5,FX!$A$5:$A$8,0))) -> 29.9 | K5: Markdowns −7% to −44%; −10% first order; free delivery in Europe from 68 € | L5: 45471 | M5: =IF(L5="","",'Read me'!$B$3-L5) -> 829 | N5: 3405 | O5: 95 | P5: 46276 | Q5: =IF(P5="","",'Read me'!$B$3-P5) -> 24
A6: 2 | B6: Mium Lab (ex Les Miraculeux) | C6: https://www.miumlab.com | D6: Open Ad Library | E6: Sugar-free functional gummies (saffron, sleep, hair, immunity…) | F6: Yes – gummies only | G6: Saffron + B6 gummies, 1 jar (21 days) | H6: 21.9 | I6: EUR | J6: =IF(H6="","",H6*INDEX(FX!$B$5:$B$8,MATCH(I6,FX!$A$5:$A$8,0))) -> 21.9 | K6: −15% on 4 jars (74.40 €); −10% subscription; −15% first order | L6: 44628 | M6: =IF(L6="","",'Read me'!$B$3-L6) -> 1672 | N6: 3386 | O6: 299 | P6: 45958 | Q6: =IF(P6="","",'Read me'!$B$3-P6) -> 342
A7: 3 | B7: Harmova | C7: https://harmova.com | D7: Open Ad Library | E7: Intimate-health gummies for women | F7: Yes – gummies only | G7: Gummies Équilibre Intime | H7: 34 | I7: EUR | J7: =IF(H7="","",H7*INDEX(FX!$B$5:$B$8,MATCH(I7,FX!$A$5:$A$8,0))) -> 34 | K7: "Fresh Days" 1+1 FREE | L7: 45759 | M7: =IF(L7="","",'Read me'!$B$3-L7) -> 541 | N7: 2555 | O7: 269 | P7: 46125 | Q7: =IF(P7="","",'Read me'!$B$3-P7) -> 175 | R7: Shop displayed USD 34 to our scraper; EUR price assumed equal – check the link.
A8: 4 | B8: Lashilé Beauty | C8: https://www.lashilebeauty.com | D8: Open Ad Library | E8: Hair, beauty, tanning & slimming gummies (French DTC, Cooper group) | F8: Yes – gummies only | G8: Hair growth & fortification gummies – 3-month pack (lowest price shown) | H8: 59.9 | I8: EUR | J8: =IF(H8="","",H8*INDEX(FX!$B$5:$B$8,MATCH(I8,FX!$A$5:$A$8,0))) -> 59.9 | K8: Bundle prices (e.g. 104.60 → 79.90 €); free express delivery in France; loyalty points | L8: 45162 | M8: =IF(L8="","",'Read me'!$B$3-L8) -> 1138 | N8: 2550 | O8: 317 | P8: 45917 | Q8: =IF(P8="","",'Read me'!$B$3-P8) -> 383 | R8: Also advertises in BE, DE, IT, ES, NL, AT, IE and in CEE.
A9: 5 | B9: Luxéol | C9: https://luxeol.com | D9: Open Ad Library | E9: Hair-growth supplements (capsules) & hair care | F9: No (capsules) | G9: Pousse Croissance & Fortification, 1 box (advertised) | H9: 39.8 | I9: EUR | J9: =IF(H9="","",H9*INDEX(FX!$B$5:$B$8,MATCH(I9,FX!$A$5:$A$8,0))) -> 39.8 | K9: −30% sitewide with code AUTOMNE30 + free conditioner from 50 €; 2 boxes −6% | L9: 45329 | M9: =IF(L9="","",'Read me'!$B$3-L9) -> 971 | N9: 2309 | O9: 1289 | P9: 45588 | Q9: =IF(P9="","",'Read me'!$B$3-P9) -> 712
A10: 6 | B10: Valebio | C10: https://www.valebio.com | D10: Open Ad Library | E10: French clean-label supplements (slimming, sleep, beauty) – also in 300+ pharmacies | F10: No (capsules) | G10: Brûleur+ thermogenesis, 60 caps (advertised) | H10: 30.9 | I10: EUR | J10: =IF(H10="","",H10*INDEX(FX!$B$5:$B$8,MATCH(I10,FX!$A$5:$A$8,0))) -> 30.9 | K10: Free delivery from 39.90 € | L10: 45505 | M10: =IF(L10="","",'Read me'!$B$3-L10) -> 795 | N10: 1335 | O10: 139 | P10: 46141 | Q10: =IF(P10="","",'Read me'!$B$3-P10) -> 159
A11: 7 | B11: Naturactive | C11: https://www.naturactive.fr | D11: Open Ad Library | E11: Pierre Fabre herbal supplements (capsules, essential oils) | F11: No (capsules) | G11: Règles Douloureuses capsules (advertised) | H11: 7.1 | I11: EUR | J11: =IF(H11="","",H11*INDEX(FX!$B$5:$B$8,MATCH(I11,FX!$A$5:$A$8,0))) -> 7.1 | K11: −20% on basket; −25% on Sériane range; free delivery from 39 € | L11: 46090 | M11: =IF(L11="","",'Read me'!$B$3-L11) -> 210 | N11: 91 | O11: 11 | P11: 46268 | Q11: =IF(P11="","",'Read me'!$B$3-P11) -> 32
A12: 8 | B12: Dosé | C12: https://dose-labo.com | D12: Open Ad Library | E12: Vitamin gummies & powders (new French brand, launch campaign) | F12: Yes (Créa Gummies = bestseller) | G12: Créa Gummies (creatine 3 g) | H12: 34.9 | I12: EUR | J12: =IF(H12="","",H12*INDEX(FX!$B$5:$B$8,MATCH(I12,FX!$A$5:$A$8,0))) -> 34.9 | K12: 27.92 € with subscription; free delivery from 39 €; free gift from 50 €; 30-day money-back | L12: 46300 | M12: =IF(L12="","",'Read me'!$B$3-L12) -> 0 | N12: 26 | O12: 26 | P12: 46300 | Q12: =IF(P12="","",'Read me'!$B$3-P12) -> 0

Sheet Germany
A1: Germany – stores selling gummies / supplements with Meta ads
A2: 8 stores · Meta data collected on the date in 'Read me'!B3 · sorted by number of ads
A4: # | B4: Store | C4: Store link | D4: Meta Ad Library link | E4: What they sell | F4: Sells gummies? | G4: Entry product | H4: Entry price (local) | I4: Currency | J4: Entry price (EUR) | K4: Offer | L4: Oldest ad in Ad Library (active or not) | M4: Days since oldest ad | N4: Ads in Ad Library (total) | O4: Active ads now | P4: Oldest live ad: start date | Q4: Days since oldest live ad | R4: Notes
A5: 1 | B5: ahead | C5: https://www.ahead-nutrition.com | D5: Open Ad Library | E5: Low-sugar fruit gummies (candy, not supplements) | F5: Yes – candy gummies | G5: Mini tasting pack 6 × 50 g | H5: 14.99 | I5: EUR | J5: =IF(H5="","",H5*INDEX(FX!$B$5:$B$8,MATCH(I5,FX!$A$5:$A$8,0))) -> 14.99 | K5: Tasting packs; free shipping from 49 € | L5: 45181 | M5: =IF(L5="","",'Read me'!$B$3-L5) -> 1119 | N5: 15046 | O5: 2636 | P5: 46238 | Q5: =IF(P5="","",'Read me'!$B$3-P5) -> 62 | R5: Sugar-reduced sweets, not food supplements.
A6: 2 | B6: ESN | C6: https://www.esn.com | D6: Open Ad Library | E6: Sports nutrition incl. creatine gummies (one page for many countries) | F6: Yes (creatine gummies) | G6: Creatine Gummies | H6: 27.9 | I6: EUR | J6: =IF(H6="","",H6*INDEX(FX!$B$5:$B$8,MATCH(I6,FX!$A$5:$A$8,0))) -> 27.9 | K6: −20% on Hydration & Immunity; −15% for new members | L6: 45888 | M6: =IF(L6="","",'Read me'!$B$3-L6) -> 412 | N6: 5847 | O6: 1360 | P6: 46245 | Q6: =IF(P6="","",'Read me'!$B$3-P6) -> 55 | R6: One ESN page runs ads in DE, FR, IT, NL/BE, AT.
A7: 3 | B7: Bears with Benefits | C7: https://www.bears-with-benefits.com | D7: Open Ad Library | E7: Vitamin gummy bears (hair, PMS, sleep, shape…) – EU market leader | F7: Yes – gummies only | G7: Promo bundle (from) | H7: 49.9 | I7: EUR | J7: =IF(H7="","",H7*INDEX(FX!$B$5:$B$8,MATCH(I7,FX!$A$5:$A$8,0))) -> 49.9 | K7: Promo sets up to −24%; extra discount with code GRATISSHAPE; free shipping in DE & AT from 49 € | L7: 44166 | M7: =IF(L7="","",'Read me'!$B$3-L7) -> 2134 | N7: 2693 | O7: 218 | P7: 46034 | Q7: =IF(P7="","",'Read me'!$B$3-P7) -> 266 | R7: Owned by Havea (FR). Same page serves DE and AT.
A8: 4 | B8: Hormonella | C8: https://hormonella.co | D8: Open Ad Library | E8: Hormone-balance supplements for women (plant extracts, micronutrients) | F8: No (capsules) | G8: Single complex (from) | H8: 12.95 | I8: EUR | J8: =IF(H8="","",H8*INDEX(FX!$B$5:$B$8,MATCH(I8,FX!$A$5:$A$8,0))) -> 12.95 | K8: Balance programme bundle 199 € | L8: 45812 | M8: =IF(L8="","",'Read me'!$B$3-L8) -> 488 | N8: 2122 | O8: 44 | P8: 46137 | Q8: =IF(P8="","",'Read me'!$B$3-P8) -> 163
A9: 5 | B9: femiPore (Femipure) | C9: https://femipore.de | D9: Open Ad Library | E9: Women's intimate-health gummies (pH, moisture, balance) | F9: Yes – gummies only | G9: Intimate-balance gummies, 1 pack | H9: 29.99 | I9: EUR | J9: =IF(H9="","",H9*INDEX(FX!$B$5:$B$8,MATCH(I9,FX!$A$5:$A$8,0))) -> 29.99 | K9: 57% autumn discount (49.99 → 29.99 €); 20% coupon; 90-day guarantee | L9: 45788 | M9: =IF(L9="","",'Read me'!$B$3-L9) -> 512 | N9: 1632 | O9: 43 | P9: 46154 | Q9: =IF(P9="","",'Read me'!$B$3-P9) -> 146
A10: 6 | B10: wowtamins | C10: https://www.wowtamins.de | D10: Open Ad Library | E10: Kids & teens gummies (omega-3, magnesium, vitamins) | F10: Yes – gummies only | G10: Magnesium gummies (sugar-free) | H10: 19.9 | I10: EUR | J10: =IF(H10="","",H10*INDEX(FX!$B$5:$B$8,MATCH(I10,FX!$A$5:$A$8,0))) -> 19.9 | K10: Multi-buy savings (save 3.98 € / 11.92 €); 10–15% discount codes; free shipping from 25 € | L10: 45592 | M10: =IF(L10="","",'Read me'!$B$3-L10) -> 708 | N10: 321 | O10: 55 | P10: 46129 | Q10: =IF(P10="","",'Read me'!$B$3-P10) -> 171
A11: 7 | B11: H.P.N | C11: https://hpn-store.de | D11: Open Ad Library | E11: Sports supplements (creatine, multi) | F11: No (powder/capsules) | G11: Creatine+ (advertised) | H11: 28.49 | I11: EUR | J11: =IF(H11="","",H11*INDEX(FX!$B$5:$B$8,MATCH(I11,FX!$A$5:$A$8,0))) -> 28.49 | K11: −5% (29.99 → 28.49 €); −1.50 € with code ALEXHPN; 10% insider discount | L11: 45944 | M11: =IF(L11="","",'Read me'!$B$3-L11) -> 356 | N11: 216 | O11: 11 | P11: 46088 | Q11: =IF(P11="","",'Read me'!$B$3-P11) -> 212
A12: 8 | B12: 69 Days Ladies by ALEX & MARIE (bettertaste) | C12: https://bettertaste.shop | D12: Open Ad Library | E12: Diet & protein foods + "Yummy Mummy" supplement | F12: No | G12: Erythritol sugar substitute (cheapest) | H12: 11.9 | I12: EUR | J12: =IF(H12="","",H12*INDEX(FX!$B$5:$B$8,MATCH(I12,FX!$A$5:$A$8,0))) -> 11.9 | K12: Free recipe e-book with Yummy Mummy; protein creams −30% | L12: 45386 | M12: =IF(L12="","",'Read me'!$B$3-L12) -> 914 | N12: 209 | O12: 83 | P12: 45670 | Q12: =IF(P12="","",'Read me'!$B$3-P12) -> 630

Sheet Italy
A1: Italy – stores selling gummies / supplements with Meta ads
A2: 9 stores · Meta data collected on the date in 'Read me'!B3 · sorted by number of ads
A4: # | B4: Store | C4: Store link | D4: Meta Ad Library link | E4: What they sell | F4: Sells gummies? | G4: Entry product | H4: Entry price (local) | I4: Currency | J4: Entry price (EUR) | K4: Offer | L4: Oldest ad in Ad Library (active or not) | M4: Days since oldest ad | N4: Ads in Ad Library (total) | O4: Active ads now | P4: Oldest live ad: start date | Q4: Days since oldest live ad | R4: Notes
A5: 1 | B5: Sensilab.it | C5: https://www.sensilab.it | D5: Open Ad Library | E5: Own-brand supplements (weight loss, detox, hormones) – Slovenian group | F5: Some | G5: Testosterone-support supplement (cheapest bestseller) | H5: 17.99 | I5: EUR | J5: =IF(H5="","",H5*INDEX(FX!$B$5:$B$8,MATCH(I5,FX!$A$5:$A$8,0))) -> 17.99 | K5: Bestsellers −11% to −50%; extra 10% saving (ads); free shipping over 50 € | L5: 45432 | M5: =IF(L5="","",'Read me'!$B$3-L5) -> 868 | N5: 2122 | O5: 245 | P5: 46104 | Q5: =IF(P5="","",'Read me'!$B$3-P5) -> 196
A6: 2 | B6: N2 Natural Nutrition | C6: https://www.n2naturalnutrition.it | D6: Open Ad Library | E6: Probiotics, berberine, wellness supplements | F6: No (capsules/powders) | G6: Wellness supplement (cheapest) | H6: 16.99 | I6: EUR | J6: =IF(H6="","",H6*INDEX(FX!$B$5:$B$8,MATCH(I6,FX!$A$5:$A$8,0))) -> 16.99 | K6: Markdowns −10% to −29% (e.g. Women's Symbiotics 35.00 → 24.95 €) | L6: 45609 | M6: =IF(L6="","",'Read me'!$B$3-L6) -> 691 | N6: 1954 | O6: 148 | P6: 45827 | Q6: =IF(P6="","",'Read me'!$B$3-P6) -> 473
A7: 3 | B7: Avanelle | C7: https://avanellelab.com | D7: Open Ad Library | E7: Creatine gummies (US DTC brand) | F7: Yes – gummies only | G7: Creatine gummies (strawberry), 1 pack | H7: 59.99 | I7: USD | J7: =IF(H7="","",H7*INDEX(FX!$B$5:$B$8,MATCH(I7,FX!$A$5:$A$8,0))) -> 55.1908 | K7: 15% off everything; Buy 2 + 1 free; Buy 3 + 2 free; free shipping on subscription | L7: 46070 | M7: =IF(L7="","",'Read me'!$B$3-L7) -> 230 | N7: 1465 | O7: 111 | P7: 46293 | Q7: =IF(P7="","",'Read me'!$B$3-P7) -> 7 | R7: Not Italian: a US brand whose ads reach Italy/Belgium/NL; prices in USD.
A8: 4 | B8: French Mush Italia | C8: https://www.frenchmush.com/it | D8: Open Ad Library | E8: Functional mushroom supplements (capsules, coffee alternative) | F8: No (capsules/powders) | G8: Boost coffee alternative (one-time) | H8: 29.9 | I8: EUR | J8: =IF(H8="","",H8*INDEX(FX!$B$5:$B$8,MATCH(I8,FX!$A$5:$A$8,0))) -> 29.9 | K8: Markdowns up to −44%; −10% first order; free delivery in Europe from 68 € | L8: 45674 | M8: =IF(L8="","",'Read me'!$B$3-L8) -> 626 | N8: 1264 | O8: 65 | P8: 46238 | Q8: =IF(P8="","",'Read me'!$B$3-P8) -> 62 | R8: Italian page of the French brand French Mush.
A9: 5 | B9: Bears with Benefits Italia | C9: https://www.bears-with-benefits.it | D9: Open Ad Library | E9: Vitamin gummy bears (hair, slimming, sleep…) | F9: Yes – gummies only | G9: Burn Baby Burn gummies (45 days) | H9: 27.9 | I9: EUR | J9: =IF(H9="","",H9*INDEX(FX!$B$5:$B$8,MATCH(I9,FX!$A$5:$A$8,0))) -> 27.9 | K9: −19% (advertised); promo sets up to −24%; free shipping | L9: 45642 | M9: =IF(L9="","",'Read me'!$B$3-L9) -> 658 | N9: 1250 | O9: 182 | P9: 46154 | Q9: =IF(P9="","",'Read me'!$B$3-P9) -> 146
A10: 6 | B10: Vitastrong.it | C10: https://www.vitastrong.it | D10: Open Ad Library | E10: Italian sports & wellness supplements + ambassador programme | F10: No (powders/tablets) | G10: Tablets 150 cpr (reduce tiredness) | H10: 19.99 | I10: EUR | J10: =IF(H10="","",H10*INDEX(FX!$B$5:$B$8,MATCH(I10,FX!$A$5:$A$8,0))) -> 19.99 | K10: Markdowns −9% to −40% (e.g. creatine 23.99 → 19.99 €); free shipping over 19.90 €; ambassador ads | L10: 45580 | M10: =IF(L10="","",'Read me'!$B$3-L10) -> 720 | N10: 922 | O10: 78 | P10: 46090 | Q10: =IF(P10="","",'Read me'!$B$3-P10) -> 210
A11: 7 | B11: NutriSonno | C11: https://nutri-sonno.com | D11: Open Ad Library | E11: Magnesium bisglycinate gummies (sleep) – advertorial funnel | F11: Yes – gummies only | G11: Magnesium gummies, 1 bag (1 month) | H11: 29.9 | I11: EUR | J11: =IF(H11="","",H11*INDEX(FX!$B$5:$B$8,MATCH(I11,FX!$A$5:$A$8,0))) -> 29.9 | K11: 39.90 → 29.90 €; 2 bags 44.90 €; 3 bags + 1 free 79.90 €; "promo ending" countdown | L11: 46246 | M11: =IF(L11="","",'Read me'!$B$3-L11) -> 54 | N11: 197 | O11: 146 | P11: 46271 | Q11: =IF(P11="","",'Read me'!$B$3-P11) -> 29
A12: 8 | B12: Zymerex | C12: https://www.zymerex.it | D12: Open Ad Library | E12: Herbal supplements (anxiety, regularity, magnesium) | F12: No | G12: Magnesium (Amazon store, −53%) | H12: 6.55 | I12: EUR | J12: =IF(H12="","",H12*INDEX(FX!$B$5:$B$8,MATCH(I12,FX!$A$5:$A$8,0))) -> 6.55 | K12: Amazon store markdowns −5% to −53% | L12: 45847 | M12: =IF(L12="","",'Read me'!$B$3-L12) -> 453 | N12: 54 | O12: 35 | P12: 45847 | Q12: =IF(P12="","",'Read me'!$B$3-P12) -> 453 | R12: Ads link to the brand's Amazon store.
A13: 9 | B13: PrinFit | C13: https://www.prinfit.com | D13: Open Ad Library | E13: Italian sports & wellness supplements | F13: Some | G13: Cheapest product (from) | H13: 12.9 | I13: EUR | J13: =IF(H13="","",H13*INDEX(FX!$B$5:$B$8,MATCH(I13,FX!$A$5:$A$8,0))) -> 12.9 | K13: Markdowns (e.g. 17.90 → 12.90 €, 31.90 → 21.90 €) | L13: 45480 | M13: =IF(L13="","",'Read me'!$B$3-L13) -> 820 | N13: 46 | O13: 17 | P13: 46121 | Q13: =IF(P13="","",'Read me'!$B$3-P13) -> 179

Sheet Belgium
A1: Belgium – stores selling gummies / supplements with Meta ads
A2: 8 stores · Meta data collected on the date in 'Read me'!B3 · sorted by number of ads
A4: # | B4: Store | C4: Store link | D4: Meta Ad Library link | E4: What they sell | F4: Sells gummies? | G4: Entry product | H4: Entry price (local) | I4: Currency | J4: Entry price (EUR) | K4: Offer | L4: Oldest ad in Ad Library (active or not) | M4: Days since oldest ad | N4: Ads in Ad Library (total) | O4: Active ads now | P4: Oldest live ad: start date | Q4: Days since oldest live ad | R4: Notes
A5: 1 | B5: Kruidvat België/Belgique | C5: https://www.kruidvat.be | D5: Open Ad Library | E5: Drugstore chain: health, vitamins, Lucovitaal supplements | F5: Yes (multi-brand) | I5: EUR | J5: =IF(H5="","",H5*INDEX(FX!$B$5:$B$8,MATCH(I5,FX!$A$5:$A$8,0))) | K5: Lucovitaal range 1+1 free; 2+1 free on Kruidvat multivitamins | L5: 45749 | M5: =IF(L5="","",'Read me'!$B$3-L5) -> 551 | N5: 3065 | O5: 269 | P5: 46069 | Q5: =IF(P5="","",'Read me'!$B$3-P5) -> 231
A6: 2 | B6: Harmova | C6: https://harmova.com | D6: Open Ad Library | E6: Intimate-health gummies for women | F6: Yes – gummies only | G6: Gummies Équilibre Intime | H6: 34 | I6: EUR | J6: =IF(H6="","",H6*INDEX(FX!$B$5:$B$8,MATCH(I6,FX!$A$5:$A$8,0))) -> 34 | K6: "Fresh Days" 1+1 FREE | L6: 45759 | M6: =IF(L6="","",'Read me'!$B$3-L6) -> 541 | N6: 2555 | O6: 269 | P6: 46125 | Q6: =IF(P6="","",'Read me'!$B$3-P6) -> 175 | R6: Same page as France.
A7: 3 | B7: Lashilé Beauty | C7: https://www.lashilebeauty.com | D7: Open Ad Library | E7: Hair, beauty, tanning & slimming gummies (French DTC) | F7: Yes – gummies only | G7: Hair growth & fortification gummies – 3-month pack | H7: 59.9 | I7: EUR | J7: =IF(H7="","",H7*INDEX(FX!$B$5:$B$8,MATCH(I7,FX!$A$5:$A$8,0))) -> 59.9 | K7: Bundle prices (e.g. 104.60 → 79.90 €); loyalty points | L7: 45162 | M7: =IF(L7="","",'Read me'!$B$3-L7) -> 1138 | N7: 2550 | O7: 317 | P7: 45917 | Q7: =IF(P7="","",'Read me'!$B$3-P7) -> 383 | R7: Same page as France.
A8: 4 | B8: Farmaline | C8: https://www.farmaline.be | D8: Open Ad Library | E8: Belgian online pharmacy (shop-apotheke group) | F8: Yes (multi-brand) | G8: Multivitamin (from, −34%) | H8: 14.89 | I8: EUR | J8: =IF(H8="","",H8*INDEX(FX!$B$5:$B$8,MATCH(I8,FX!$A$5:$A$8,0))) -> 14.89 | K8: Up to −38%; €5 newsletter code; free shipping thresholds; app promos | L8: 45036 | M8: =IF(L8="","",'Read me'!$B$3-L8) -> 1264 | N8: 919 | O8: 171 | P8: 45726 | Q8: =IF(P8="","",'Read me'!$B$3-P8) -> 574
A9: 5 | B9: AlphaVit | C9: https://alphavit-officiel.com | D9: Open Ad Library | E9: Gummy supplement (single product, French-language DTC) | F9: Yes – gummies only | G9: Alphavit gummies – 2 bags (1+1 free, 60 days) | H9: 34.99 | I9: EUR | J9: =IF(H9="","",H9*INDEX(FX!$B$5:$B$8,MATCH(I9,FX!$A$5:$A$8,0))) -> 34.99 | K9: 1+1 FREE (2 bags for 34.99 € instead of 69.98 €); delivery included | L9: 46062 | M9: =IF(L9="","",'Read me'!$B$3-L9) -> 238 | N9: 842 | O9: 127 | P9: 46220 | Q9: =IF(P9="","",'Read me'!$B$3-P9) -> 80 | R9: French-language store; ads target Belgium and France.
A10: 6 | B10: Bears with Benefits (NL/BE) | C10: https://www.bears-with-benefits.nl | D10: Open Ad Library | E10: Vitamin gummy bears | F10: Yes – gummies only | G10: Gummy bears, 1 pack (offer) | H10: 27.9 | I10: EUR | J10: =IF(H10="","",H10*INDEX(FX!$B$5:$B$8,MATCH(I10,FX!$A$5:$A$8,0))) -> 27.9 | K10: Free delivery in NL & BE from 29 € | L10: 45642 | M10: =IF(L10="","",'Read me'!$B$3-L10) -> 658 | N10: 402 | O10: 65 | P10: 46190 | Q10: =IF(P10="","",'Read me'!$B$3-P10) -> 110 | R10: Same page as the Netherlands.
A11: 7 | B11: Santurel | C11: https://www.santurel.net | D11: Open Ad Library | E11: Belgian science-based supplements (sleep, eyes, magnesium, ashwagandha) | F11: No (capsules) | G11: Somnia sleep capsules, 90 caps (advertised) | H11: 44.95 | I11: EUR | J11: =IF(H11="","",H11*INDEX(FX!$B$5:$B$8,MATCH(I11,FX!$A$5:$A$8,0))) -> 44.95 | K11: −12% from 3 jars of the same product; bundles; free delivery from 40 € | L11: 46238 | M11: =IF(L11="","",'Read me'!$B$3-L11) -> 62 | N11: 98 | O11: 82 | P11: 46262 | Q11: =IF(P11="","",'Read me'!$B$3-P11) -> 38
A12: 8 | B12: Decola Nutraceutics | C12: https://www.decola.be | D12: Open Ad Library | E12: Belgian premium supplements (OPC, glucosamine, cognition) | F12: No (capsules) | G12: OPC (bestseller) | H12: 34.7 | I12: EUR | J12: =IF(H12="","",H12*INDEX(FX!$B$5:$B$8,MATCH(I12,FX!$A$5:$A$8,0))) -> 34.7 | K12: Newsletter promotions | L12: 46001 | M12: =IF(L12="","",'Read me'!$B$3-L12) -> 299 | N12: 12 | O12: 5 | P12: 46170 | Q12: =IF(P12="","",'Read me'!$B$3-P12) -> 130

Sheet Netherlands
A1: Netherlands – stores selling gummies / supplements with Meta ads
A2: 9 stores · Meta data collected on the date in 'Read me'!B3 · sorted by number of ads
A4: # | B4: Store | C4: Store link | D4: Meta Ad Library link | E4: What they sell | F4: Sells gummies? | G4: Entry product | H4: Entry price (local) | I4: Currency | J4: Entry price (EUR) | K4: Offer | L4: Oldest ad in Ad Library (active or not) | M4: Days since oldest ad | N4: Ads in Ad Library (total) | O4: Active ads now | P4: Oldest live ad: start date | Q4: Days since oldest live ad | R4: Notes
A5: 1 | B5: WeightWorld | C5: https://www.weightworld.nl | D5: Open Ad Library | E5: Multi-product supplements webshop (gummies, capsules) | F5: Yes (some gummies) | G5: Omega-3 240 softgels (offer) | H5: 21.99 | I5: EUR | J5: =IF(H5="","",H5*INDEX(FX!$B$5:$B$8,MATCH(I5,FX!$A$5:$A$8,0))) -> 21.99 | K5: Sale page (24.99 → 21.99 €); free shipping | L5: 45457 | M5: =IF(L5="","",'Read me'!$B$3-L5) -> 843 | N5: 3898 | O5: 171 | P5: 46080 | Q5: =IF(P5="","",'Read me'!$B$3-P5) -> 220
A6: 2 | B6: Ahead Nederland | C6: https://www.ahead-nutrition.com/nl-nl | D6: Open Ad Library | E6: Low-sugar fruit gummies (candy, not supplements) | F6: Yes – candy gummies | G6: Gummies proefbox 12 × 50 g | H6: 24.99 | I6: EUR | J6: =IF(H6="","",H6*INDEX(FX!$B$5:$B$8,MATCH(I6,FX!$A$5:$A$8,0))) -> 24.99 | K6: Tasting box; free shipping thresholds | L6: 45895 | M6: =IF(L6="","",'Read me'!$B$3-L6) -> 405 | N6: 2585 | O6: 290 | P6: 46099 | Q6: =IF(P6="","",'Read me'!$B$3-P6) -> 201 | R6: Sugar-reduced sweets, not food supplements.
A7: 3 | B7: Hairlust | C7: https://hairlust.com | D7: Open Ad Library | E7: Hair-growth gummies & hair care (Danish brand) | F7: Yes (hair gummies) | I7: EUR | J7: =IF(H7="","",H7*INDEX(FX!$B$5:$B$8,MATCH(I7,FX!$A$5:$A$8,0))) | K7: Bundles (Curl Crush bundle) | L7: 45755 | M7: =IF(L7="","",'Read me'!$B$3-L7) -> 545 | N7: 2316 | O7: 1240 | P7: 45974 | Q7: =IF(P7="","",'Read me'!$B$3-P7) -> 326 | R7: Ads point to Norwegian/Danish storefronts; no NL price captured.
A8: 4 | B8: Dailipharma | C8: https://dailipharma.com | D8: Open Ad Library | E8: Liquid supplement ampoules (collagen, joints) | F8: No (liquid shots) | G8: Daili Movement, 28 ampoules (one-time) | H8: 74.9 | I8: EUR | J8: =IF(H8="","",H8*INDEX(FX!$B$5:$B$8,MATCH(I8,FX!$A$5:$A$8,0))) -> 74.9 | K8: Subscription −16% (62.92 €); always free shipping | L8: 45616 | M8: =IF(L8="","",'Read me'!$B$3-L8) -> 684 | N8: 1999 | O8: 224 | P8: 46132 | Q8: =IF(P8="","",'Read me'!$B$3-P8) -> 168
A9: 5 | B9: Vitaminfit | C9: https://vitaminfit.com | D9: Open Ad Library | E9: Vitamin syrups & drops (kids & adults) | F9: No (syrups/drops) | G9: Kids multivitamin + D3 drops (from) | H9: 18.95 | I9: EUR | J9: =IF(H9="","",H9*INDEX(FX!$B$5:$B$8,MATCH(I9,FX!$A$5:$A$8,0))) -> 18.95 | K9: Markdowns (26.95 → 22.70 €); next-day delivery | L9: 45889 | M9: =IF(L9="","",'Read me'!$B$3-L9) -> 411 | N9: 1082 | O9: 80 | P9: 46246 | Q9: =IF(P9="","",'Read me'!$B$3-P9) -> 54
A10: 6 | B10: STR Nordic | C10: https://strnordic.nl | D10: Open Ad Library | E10: Scandinavian supplements (magnesium etc.) via trial offers | F10: No | G10: Trial: 5 months for 24.95 € | H10: 24.95 | I10: EUR | J10: =IF(H10="","",H10*INDEX(FX!$B$5:$B$8,MATCH(I10,FX!$A$5:$A$8,0))) -> 24.95 | K10: "Only €24.95 for 5 months" trial incl. free shipping (then subscription) | L10: 45616 | M10: =IF(L10="","",'Read me'!$B$3-L10) -> 684 | N10: 447 | O10: 11 | P10: 46188 | Q10: =IF(P10="","",'Read me'!$B$3-P10) -> 112
A11: 7 | B11: Bears with Benefits Netherland | C11: https://www.bears-with-benefits.nl | D11: Open Ad Library | E11: Vitamin gummy bears | F11: Yes – gummies only | G11: Gummy bears, 1 pack (offer) | H11: 27.9 | I11: EUR | J11: =IF(H11="","",H11*INDEX(FX!$B$5:$B$8,MATCH(I11,FX!$A$5:$A$8,0))) -> 27.9 | K11: Sale prices; free beauty test; free delivery in NL & BE from 29 € | L11: 45642 | M11: =IF(L11="","",'Read me'!$B$3-L11) -> 658 | N11: 402 | O11: 65 | P11: 46190 | Q11: =IF(P11="","",'Read me'!$B$3-P11) -> 110
A12: 8 | B12: Puur Mieke | C12: https://www.puurmieke.nl | D12: Open Ad Library | E12: Organic food & supplements webshop | F12: Some | I12: EUR | J12: =IF(H12="","",H12*INDEX(FX!$B$5:$B$8,MATCH(I12,FX!$A$5:$A$8,0))) | K12: −10% / −20% markdowns; free shaker; free recipe book; free shipping NL & BE from 55 € | L12: 45293 | M12: =IF(L12="","",'Read me'!$B$3-L12) -> 1007 | N12: 350 | O12: 47 | P12: 45372 | Q12: =IF(P12="","",'Read me'!$B$3-P12) -> 928
A13: 9 | B13: FutuNatura.nl | C13: https://www.futunatura.nl | D13: Open Ad Library | E13: Own-brand supplements incl. gummies (Slovenian group) | F13: Yes (part of range) | G13: Sweet Dreams liquid supplement (advertised) | H13: 9.99 | I13: EUR | J13: =IF(H13="","",H13*INDEX(FX!$B$5:$B$8,MATCH(I13,FX!$A$5:$A$8,0))) -> 9.99 | K13: −15/−17% (11.99 → 9.99 €); free shipping over 39.99 €; gift over 100 € | L13: 45930 | M13: =IF(L13="","",'Read me'!$B$3-L13) -> 370 | N13: 288 | O13: 42 | P13: 45930 | Q13: =IF(P13="","",'Read me'!$B$3-P13) -> 370

Sheet Spain
A1: Spain – stores selling gummies / supplements with Meta ads
A2: 9 stores · Meta data collected on the date in 'Read me'!B3 · sorted by number of ads
A4: # | B4: Store | C4: Store link | D4: Meta Ad Library link | E4: What they sell | F4: Sells gummies? | G4: Entry product | H4: Entry price (local) | I4: Currency | J4: Entry price (EUR) | K4: Offer | L4: Oldest ad in Ad Library (active or not) | M4: Days since oldest ad | N4: Ads in Ad Library (total) | O4: Active ads now | P4: Oldest live ad: start date | Q4: Days since oldest live ad | R4: Notes
A5: 1 | B5: Aldous Bio | C5: https://aldousbio.com | D5: Open Ad Library | E5: Organic, plastic-free supplements incl. collagen gummies | F5: Yes (some gummies) | G5: Hydrolysed collagen gummies | H5: 17.57 | I5: EUR | J5: =IF(H5="","",H5*INDEX(FX!$B$5:$B$8,MATCH(I5,FX!$A$5:$A$8,0))) -> 17.57 | K5: −20% (21.97 → 17.57 €); 3 products −32%; free shipping 24–48 h | L5: 44008 | M5: =IF(L5="","",'Read me'!$B$3-L5) -> 2292 | N5: 3421 | O5: 755 | P5: 46063 | Q5: =IF(P5="","",'Read me'!$B$3-P5) -> 237
A6: 2 | B6: V-Gummies | C6: https://v-gummies.com | D6: Open Ad Library | E6: Apple-cider-vinegar gummies for women (advertorial funnels) | F6: Yes – gummies only | G6: D-Tox ACV gummies, 1 bag (25 days) | H6: 35.7 | I6: EUR | J6: =IF(H6="","",H6*INDEX(FX!$B$5:$B$8,MATCH(I6,FX!$A$5:$A$8,0))) -> 35.7 | K6: Buy 2, get 1 FREE (23.80 €/bag); Buy 3, get 2 FREE (−40%); free express shipping | L6: 46058 | M6: =IF(L6="","",'Read me'!$B$3-L6) -> 242 | N6: 1513 | O6: 309 | P6: 46148 | Q6: =IF(P6="","",'Read me'!$B$3-P6) -> 152
A7: 3 | B7: Vitobest | C7: https://www.vitobest.com | D7: Open Ad Library | E7: Spanish sports nutrition (creatine, protein) | F7: No | I7: EUR | J7: =IF(H7="","",H7*INDEX(FX!$B$5:$B$8,MATCH(I7,FX!$A$5:$A$8,0))) | L7: 45714 | M7: =IF(L7="","",'Read me'!$B$3-L7) -> 586 | N7: 1053 | O7: 86 | P7: 46111 | Q7: =IF(P7="","",'Read me'!$B$3-P7) -> 189 | R7: Site blocked our scraper (Cloudflare) – open the link for prices.
A8: 4 | B8: Bears with Benefits España | C8: https://www.bears-with-benefits.es | D8: Open Ad Library | E8: Vitamin gummy bears | F8: Yes – gummies only | G8: Ah-mazing Hair (sugar-free), 45 days | H8: 22.9 | I8: EUR | J8: =IF(H8="","",H8*INDEX(FX!$B$5:$B$8,MATCH(I8,FX!$A$5:$A$8,0))) -> 22.9 | K8: −19% (advertised); promotions up to −11% on sets; free shipping from 29 € | L8: 45642 | M8: =IF(L8="","",'Read me'!$B$3-L8) -> 658 | N8: 737 | O8: 42 | P8: 46175 | Q8: =IF(P8="","",'Read me'!$B$3-P8) -> 125
A9: 5 | B9: Primal Pump | C9: https://primalpump.es | D9: Open Ad Library | E9: Sugar-free creatine gummies | F9: Yes – gummies only | G9: Creatine gummies, 1 unit | H9: 32.49 | I9: EUR | J9: =IF(H9="","",H9*INDEX(FX!$B$5:$B$8,MATCH(I9,FX!$A$5:$A$8,0))) -> 32.49 | K9: 3 units 27.62 €/unit; 5 units 25.99 €/unit; free shipping | L9: 45913 | M9: =IF(L9="","",'Read me'!$B$3-L9) -> 387 | N9: 605 | O9: 37 | P9: 46187 | Q9: =IF(P9="","",'Read me'!$B$3-P9) -> 113
A10: 6 | B10: Laboratorios Mahen | C10: https://www.mahen.es | D10: Open Ad Library | E10: Spanish lab: hair, energy, detox, skin supplements | F10: No (capsules/liquids) | G10: Energy capsules (cheapest) | H10: 24.9 | I10: EUR | J10: =IF(H10="","",H10*INDEX(FX!$B$5:$B$8,MATCH(I10,FX!$A$5:$A$8,0))) -> 24.9 | K10: −15% with code ESPECIAL15 (in ad link); free shipping from 40 € | L10: 45783 | M10: =IF(L10="","",'Read me'!$B$3-L10) -> 517 | N10: 499 | O10: 39 | P10: 45867 | Q10: =IF(P10="","",'Read me'!$B$3-P10) -> 433
A11: 7 | B11: Sonvital | C11: https://sonvital.com | D11: Open Ad Library | E11: Lymphatic drainage / slimming supplement | F11: No | H11: 29.9 | I11: EUR | J11: =IF(H11="","",H11*INDEX(FX!$B$5:$B$8,MATCH(I11,FX!$A$5:$A$8,0))) -> 29.9 | K11: 1 unit 29.90 € (was 60 €); 2 units 49.90 €; free shipping | L11: 46135 | M11: =IF(L11="","",'Read me'!$B$3-L11) -> 165 | N11: 350 | O11: 267 | P11: 46192 | Q11: =IF(P11="","",'Read me'!$B$3-P11) -> 108 | R11: Entry product: lymphatic drainage, 2 months.
A12: 8 | B12: Femive | C12: https://www.femive.com | D12: Open Ad Library | E12: Women's gummies (chlorophyll, vaginal probiotic) | F12: Yes – gummies only | G12: Chlorophyll gummies, 30 days | H12: 29.95 | I12: EUR | J12: =IF(H12="","",H12*INDEX(FX!$B$5:$B$8,MATCH(I12,FX!$A$5:$A$8,0))) -> 29.95 | K12: 39.95 → 29.95 €; 60 gummies 44.95 €; 90 gummies 59.95 € | L12: 45985 | M12: =IF(L12="","",'Read me'!$B$3-L12) -> 315 | N12: 194 | O12: 10 | P12: 46299 | Q12: =IF(P12="","",'Read me'!$B$3-P12) -> 1
A13: 9 | B13: Arama Natural Products España | C13: https://aramanatural.es | D13: Open Ad Library | E13: Natural supplements (joints – Progen, collagen) | F13: No | I13: EUR | J13: =IF(H13="","",H13*INDEX(FX!$B$5:$B$8,MATCH(I13,FX!$A$5:$A$8,0))) | L13: 45849 | M13: =IF(L13="","",'Read me'!$B$3-L13) -> 451 | N13: 117 | O13: 6 | P13: 46259 | Q13: =IF(P13="","",'Read me'!$B$3-P13) -> 41 | R13: Site blocked our scraper.

Sheet Portugal
A1: Portugal – stores selling gummies / supplements with Meta ads
A2: 9 stores · Meta data collected on the date in 'Read me'!B3 · sorted by number of ads
A4: # | B4: Store | C4: Store link | D4: Meta Ad Library link | E4: What they sell | F4: Sells gummies? | G4: Entry product | H4: Entry price (local) | I4: Currency | J4: Entry price (EUR) | K4: Offer | L4: Oldest ad in Ad Library (active or not) | M4: Days since oldest ad | N4: Ads in Ad Library (total) | O4: Active ads now | P4: Oldest live ad: start date | Q4: Days since oldest live ad | R4: Notes
A5: 1 | B5: Sensilab.pt | C5: https://www.sensilab.pt | D5: Open Ad Library | E5: Own-brand supplements (Slovenian group) | F5: Some | G5: Hepafar forte PREMIUM (1+1 free) | H5: 19.99 | I5: EUR | J5: =IF(H5="","",H5*INDEX(FX!$B$5:$B$8,MATCH(I5,FX!$A$5:$A$8,0))) -> 19.99 | K5: 1+1 FREE on bestsellers (Hepafar, Thyrolux, Estrolux, Fat Out); −50%; free delivery over 45 € | L5: 45689 | M5: =IF(L5="","",'Read me'!$B$3-L5) -> 611 | N5: 1886 | O5: 231 | P5: 46128 | Q5: =IF(P5="","",'Read me'!$B$3-P5) -> 172
A6: 2 | B6: WeightWorld PT | C6: https://www.weightworld.com.pt | D6: Open Ad Library | E6: Multi-product supplements webshop incl. gummies | F6: Yes (some gummies) | G6: Vegan gummies 1200 mg, 120 pcs | H6: 17.49 | I6: EUR | J6: =IF(H6="","",H6*INDEX(FX!$B$5:$B$8,MATCH(I6,FX!$A$5:$A$8,0))) -> 17.49 | K6: Launch campaign "WeightWorld arrived in Portugal" | L6: 45979 | M6: =IF(L6="","",'Read me'!$B$3-L6) -> 321 | N6: 457 | O6: 64 | P6: 46238 | Q6: =IF(P6="","",'Read me'!$B$3-P6) -> 62
A7: 3 | B7: Aldous Bio Portugal | C7: https://aldousbio.pt | D7: Open Ad Library | E7: Organic, plastic-free supplements incl. collagen gummies | F7: Yes (some gummies) | G7: Hydrolysed collagen gummies | H7: 17.57 | I7: EUR | J7: =IF(H7="","",H7*INDEX(FX!$B$5:$B$8,MATCH(I7,FX!$A$5:$A$8,0))) -> 17.57 | K7: −20%; 3 products −32%; free shipping | L7: 46057 | M7: =IF(L7="","",'Read me'!$B$3-L7) -> 243 | N7: 382 | O7: 21 | P7: 46163 | Q7: =IF(P7="","",'Read me'!$B$3-P7) -> 137
A8: 4 | B8: Maxnésio | C8: https://maxnesio.pt | D8: Open Ad Library | E8: Magnesium supplements | F8: No | I8: EUR | J8: =IF(H8="","",H8*INDEX(FX!$B$5:$B$8,MATCH(I8,FX!$A$5:$A$8,0))) | L8: 45952 | M8: =IF(L8="","",'Read me'!$B$3-L8) -> 348 | N8: 247 | O8: 24 | P8: 46113 | Q8: =IF(P8="","",'Read me'!$B$3-P8) -> 187
A9: 5 | B9: Confidence-Mulher | C9: https://confidence-mulher.pt | D9: Open Ad Library | E9: (Peri)menopause supplements | F9: No | I9: EUR | J9: =IF(H9="","",H9*INDEX(FX!$B$5:$B$8,MATCH(I9,FX!$A$5:$A$8,0))) | L9: 45936 | M9: =IF(L9="","",'Read me'!$B$3-L9) -> 364 | N9: 234 | O9: 19 | P9: 46113 | Q9: =IF(P9="","",'Read me'!$B$3-P9) -> 187
A10: 6 | B10: NutriBio | C10: https://nutribio.pt | D10: Open Ad Library | E10: Supplements webshop (TomasVit, New Nordic…) | F10: Some | G10: Kids sleep syrup 150 ml (cheapest) | H10: 10.99 | I10: EUR | J10: =IF(H10="","",H10*INDEX(FX!$B$5:$B$8,MATCH(I10,FX!$A$5:$A$8,0))) -> 10.99 | K10: Buy 4 pay 3 on TomasVit; −17% to −27% markdowns; free shipping from 30 € | L10: 45208 | M10: =IF(L10="","",'Read me'!$B$3-L10) -> 1092 | N10: 214 | O10: 58 | P10: 45774 | Q10: =IF(P10="","",'Read me'!$B$3-P10) -> 526
A11: 7 | B11: Eu Sou Gira | C11: https://eusougira.com | D11: Open Ad Library | E11: Beauty & wellness supplements (GIRA) | F11: Some | I11: EUR | J11: =IF(H11="","",H11*INDEX(FX!$B$5:$B$8,MATCH(I11,FX!$A$5:$A$8,0))) | K11: Free shipping from 45 € in Portugal | L11: 45877 | M11: =IF(L11="","",'Read me'!$B$3-L11) -> 423 | N11: 178 | O11: 66 | P11: 45960 | Q11: =IF(P11="","",'Read me'!$B$3-P11) -> 340
A12: 8 | B12: Viva Melhor | C12: https://vivamelhor.pt | D12: Open Ad Library | E12: Multivitamins, magnesium, sleep & slimming supplements | F12: No | G12: Floricalm Night-Night (sleep) | H12: 27 | I12: EUR | J12: =IF(H12="","",H12*INDEX(FX!$B$5:$B$8,MATCH(I12,FX!$A$5:$A$8,0))) -> 27 | K12: Weight-loss pack on sale (65 → 55 €) | L12: 45811 | M12: =IF(L12="","",'Read me'!$B$3-L12) -> 489 | N12: 67 | O12: 6 | P12: 46021 | Q12: =IF(P12="","",'Read me'!$B$3-P12) -> 279
A13: 9 | B13: Nature Heals | C13: https://natureheals.pt | D13: Open Ad Library | E13: Natural supplements webshop (Biogena, London Nootropics…) | F13: Some | G13: Nootropic coffee 12 sachets (cheapest featured) | H13: 22.8 | I13: EUR | J13: =IF(H13="","",H13*INDEX(FX!$B$5:$B$8,MATCH(I13,FX!$A$5:$A$8,0))) -> 22.8 | K13: Promotions; free shipping from 30 € (mainland) | L13: 45965 | M13: =IF(L13="","",'Read me'!$B$3-L13) -> 335 | N13: 38 | O13: 11 | P13: 46086 | Q13: =IF(P13="","",'Read me'!$B$3-P13) -> 214

Sheet Switzerland
A1: Switzerland – stores selling gummies / supplements with Meta ads
A2: 12 stores · Meta data collected on the date in 'Read me'!B3 · sorted by number of ads
A4: # | B4: Store | C4: Store link | D4: Meta Ad Library link | E4: What they sell | F4: Sells gummies? | G4: Entry product | H4: Entry price (local) | I4: Currency | J4: Entry price (EUR) | K4: Offer | L4: Oldest ad in Ad Library (active or not) | M4: Days since oldest ad | N4: Ads in Ad Library (total) | O4: Active ads now | P4: Oldest live ad: start date | Q4: Days since oldest live ad | R4: Notes
A5: 1 | B5: Lynae | C5: https://lynae.co | D5: Open Ad Library | E5: Lymphatic-drainage supplement for women (French DTC) | F5: No (liquid) | G5: Drainant Lymphatique, 1 bottle (30 days) | H5: 24.9 | I5: EUR | J5: =IF(H5="","",H5*INDEX(FX!$B$5:$B$8,MATCH(I5,FX!$A$5:$A$8,0))) -> 24.9 | K5: Buy 2 + 1 free (16.60 €/bottle); 3 + 2 free (14.98 €); free delivery from 40 € | L5: 45996 | M5: =IF(L5="","",'Read me'!$B$3-L5) -> 304 | N5: 3464 | O5: 764 | P5: 46078 | Q5: =IF(P5="","",'Read me'!$B$3-P5) -> 222 | R5: French brand targeting Swiss French-speakers; shop shows EUR.
A6: 2 | B6: Harmova | C6: https://harmova.com | D6: Open Ad Library | E6: Intimate-health gummies for women | F6: Yes – gummies only | G6: Gummies Équilibre Intime | H6: 34 | I6: EUR | J6: =IF(H6="","",H6*INDEX(FX!$B$5:$B$8,MATCH(I6,FX!$A$5:$A$8,0))) -> 34 | K6: "Fresh Days" 1+1 FREE | L6: 45759 | M6: =IF(L6="","",'Read me'!$B$3-L6) -> 541 | N6: 2555 | O6: 269 | P6: 46125 | Q6: =IF(P6="","",'Read me'!$B$3-P6) -> 175 | R6: French brand advertising to French-speaking Switzerland; same page as France.
A7: 3 | B7: Luxéol | C7: https://luxeol.com | D7: Open Ad Library | E7: Hair-growth supplements (capsules) & hair care | F7: No (capsules) | G7: Pousse Croissance & Fortification, 1 box | H7: 39.8 | I7: EUR | J7: =IF(H7="","",H7*INDEX(FX!$B$5:$B$8,MATCH(I7,FX!$A$5:$A$8,0))) -> 39.8 | K7: −30% sitewide with code AUTOMNE30 | L7: 45329 | M7: =IF(L7="","",'Read me'!$B$3-L7) -> 971 | N7: 2309 | O7: 1289 | P7: 45588 | Q7: =IF(P7="","",'Read me'!$B$3-P7) -> 712 | R7: French brand advertising to French-speaking Switzerland; same page as France.
A8: 4 | B8: Purazell | C8: https://purazell.de | D8: Open Ad Library | E8: Liposomal vitamins, collagen, raw foods | F8: No | G8: Liposomal NADH 150 ml | H8: 25.9 | I8: EUR | J8: =IF(H8="","",H8*INDEX(FX!$B$5:$B$8,MATCH(I8,FX!$A$5:$A$8,0))) -> 25.9 | K8: "NUR" sale prices | L8: 45257 | M8: =IF(L8="","",'Read me'!$B$3-L8) -> 1043 | N8: 828 | O8: 106 | P8: 46099 | Q8: =IF(P8="","",'Read me'!$B$3-P8) -> 201 | R8: German shop advertising in Switzerland.
A9: 5 | B9: Herbano | C9: https://herbano.com/ch | D9: Open Ad Library | E9: Natural supplements & complaint-based bundles (people & pets) | F9: No (capsules) | G9: Durchschlaf sleep pack (GABA + melatonin) | H9: 52.95 | I9: CHF | J9: =IF(H9="","",H9*INDEX(FX!$B$5:$B$8,MATCH(I9,FX!$A$5:$A$8,0))) -> 56.6565 | K9: Bundles ~−10% (e.g. 69.85 → 61.95 CHF); free shipping from CHF 109.90 | L9: 45945 | M9: =IF(L9="","",'Read me'!$B$3-L9) -> 355 | N9: 176 | O9: 21 | P9: 46125 | Q9: =IF(P9="","",'Read me'!$B$3-P9) -> 175 | R9: German shop with a Swiss storefront.
A10: 6 | B10: Feelgood-Shop | C10: https://www.feelgood-shop.com | D10: Open Ad Library | E10: Online supplement shop (omega-3, vitamins, minerals) | F10: Some | G10: Vegan supplement (cheapest featured) | H10: 9.74 | I10: EUR | J10: =IF(H10="","",H10*INDEX(FX!$B$5:$B$8,MATCH(I10,FX!$A$5:$A$8,0))) -> 9.74 | K10: Markdowns −5% to −30%; 10% newsletter code; shipping to Switzerland 5.90 € | L10: 45663 | M10: =IF(L10="","",'Read me'!$B$3-L10) -> 637 | N10: 56 | O10: 7 | P10: 46171 | Q10: =IF(P10="","",'Read me'!$B$3-P10) -> 129 | R10: German shop shipping to Switzerland (prices in EUR).
A11: 7 | B11: Kanela | C11: https://kanela.ch | D11: Open Ad Library | E11: Swiss online drugstore (supplements, natural remedies) | F11: Some | G11: BIOnaturis Hirse Plus capsules, 120 pcs (advertised brand) | H11: 29.61 | I11: CHF | J11: =IF(H11="","",H11*INDEX(FX!$B$5:$B$8,MATCH(I11,FX!$A$5:$A$8,0))) -> 31.6827 | K11: BIOnaturis −10% / −25% / −33%; free shipping from CHF 100; buy on invoice | L11: 45190 | M11: =IF(L11="","",'Read me'!$B$3-L11) -> 1110 | N11: 55 | O11: 55 | P11: 45190 | Q11: =IF(P11="","",'Read me'!$B$3-P11) -> 1110
A12: 8 | B12: Nurnatur Würzenbach Drogerie | C12: https://www.nurnatur.ch | D12: Open Ad Library | E12: Swiss drugstore with natural-remedy house brands | F12: No | I12: CHF | J12: =IF(H12="","",H12*INDEX(FX!$B$5:$B$8,MATCH(I12,FX!$A$5:$A$8,0))) | L12: 45852 | M12: =IF(L12="","",'Read me'!$B$3-L12) -> 448 | N12: 25 | O12: 26 | P12: 45852 | Q12: =IF(P12="","",'Read me'!$B$3-P12) -> 448
A13: 9 | B13: Magnesium Biomed UNO | C13: https://www.magnesium-biomed.ch | D13: Open Ad Library | E13: Swiss magnesium supplements (Biomed AG) | F13: No (sachets/tablets) | I13: CHF | J13: =IF(H13="","",H13*INDEX(FX!$B$5:$B$8,MATCH(I13,FX!$A$5:$A$8,0))) | L13: 45879 | M13: =IF(L13="","",'Read me'!$B$3-L13) -> 421 | N13: 23 | O13: 26 | P13: 46243 | Q13: =IF(P13="","",'Read me'!$B$3-P13) -> 57
A14: 10 | B14: Bodysport | C14: https://bodysport.ch | D14: Open Ad Library | E14: Swiss sport nutrition & wellness shop (Alpine Labs etc.) | F14: Some | G14: Cheapest bestseller | H14: 4.9 | I14: CHF | J14: =IF(H14="","",H14*INDEX(FX!$B$5:$B$8,MATCH(I14,FX!$A$5:$A$8,0))) -> 5.243 | K14: Promotions; free delivery from CHF 80 | L14: 46098 | M14: =IF(L14="","",'Read me'!$B$3-L14) -> 202 | N14: 10 | O14: 10 | P14: 46098 | Q14: =IF(P14="","",'Read me'!$B$3-P14) -> 202
A15: 11 | B15: PlantaVis Beauty | C15: https://www.plantavis.ch | D15: Open Ad Library | E15: Swiss natural supplements (D3/K2, menopause, liver, collagen drink) | F15: No (capsules/powders) | G15: Curcuma & frankincense capsules | H15: 24.9 | I15: CHF | J15: =IF(H15="","",H15*INDEX(FX!$B$5:$B$8,MATCH(I15,FX!$A$5:$A$8,0))) -> 26.643 | K15: Free shipping from CHF 80 (else CHF 8); pay by invoice | L15: 45748 | M15: =IF(L15="","",'Read me'!$B$3-L15) -> 552 | N15: 3 | O15: 3 | P15: 45748 | Q15: =IF(P15="","",'Read me'!$B$3-P15) -> 552
A16: 12 | B16: Helvilab | C16: https://helvilab.com | D16: Open Ad Library | E16: Swiss supplements (prostate, hormones, sugar & fat metabolism, joints) | F16: No (capsules) | G16: Bestseller capsules (from) | H16: 49.95 | I16: CHF | J16: =IF(H16="","",H16*INDEX(FX!$B$5:$B$8,MATCH(I16,FX!$A$5:$A$8,0))) -> 53.4465 | K16: 25% off entire range; 10% newsletter; 15-day money-back | L16: 46079 | M16: =IF(L16="","",'Read me'!$B$3-L16) -> 221 | N16: 3 | O16: 3 | P16: 46079 | Q16: =IF(P16="","",'Read me'!$B$3-P16) -> 221

Sheet Ireland
A1: Ireland – stores selling gummies / supplements with Meta ads
A2: 8 stores · Meta data collected on the date in 'Read me'!B3 · sorted by number of ads
A4: # | B4: Store | C4: Store link | D4: Meta Ad Library link | E4: What they sell | F4: Sells gummies? | G4: Entry product | H4: Entry price (local) | I4: Currency | J4: Entry price (EUR) | K4: Offer | L4: Oldest ad in Ad Library (active or not) | M4: Days since oldest ad | N4: Ads in Ad Library (total) | O4: Active ads now | P4: Oldest live ad: start date | Q4: Days since oldest live ad | R4: Notes
A5: 1 | B5: Novomins Nutrition | C5: https://novomins.com | D5: Open Ad Library | E5: Sugar-free gummies (multivitamin, creatine, kids) | F5: Yes – gummies only | G5: Kids Calm & Collected bundle | H5: 41 | I5: USD | J5: =IF(H5="","",H5*INDEX(FX!$B$5:$B$8,MATCH(I5,FX!$A$5:$A$8,0))) -> 37.72 | K5: Women's bundle 50% off; free cap over a spend threshold; no customs fees | L5: 45796 | M5: =IF(L5="","",'Read me'!$B$3-L5) -> 504 | N5: 4283 | O5: 531 | P5: 46055 | Q5: =IF(P5="","",'Read me'!$B$3-P5) -> 245 | R5: Shop showed USD to our scraper (geo-pricing); EUR price on the Irish site may differ.
A6: 2 | B6: Beleaze | C6: https://www.beleaze.com | D6: Open Ad Library | E6: Zeolite detox gummies for kids (US) | F6: Yes – gummies only | G6: Kids zeolite detox gummies | H6: 19.8 | I6: USD | J6: =IF(H6="","",H6*INDEX(FX!$B$5:$B$8,MATCH(I6,FX!$A$5:$A$8,0))) -> 18.216 | K6: −20% subscribe; free shipping over $50 / on first order | L6: 45893 | M6: =IF(L6="","",'Read me'!$B$3-L6) -> 407 | N6: 3890 | O6: 190 | P6: 46092 | Q6: =IF(P6="","",'Read me'!$B$3-P6) -> 208 | R6: US store, prices in USD.
A7: 3 | B7: UltimaPeak | C7: https://ultimapeak.com | D7: Open Ad Library | E7: Shilajit gummies for men (quiz funnel) | F7: Yes – gummies only | G7: Shilajit daily gummies, 1 pack | H7: 39 | I7: USD | J7: =IF(H7="","",H7*INDEX(FX!$B$5:$B$8,MATCH(I7,FX!$A$5:$A$8,0))) -> 35.88 | K7: "Up to 70% off today"; Buy 2 get 1 free; Buy 3 get 2 free | L7: 46258 | M7: =IF(L7="","",'Read me'!$B$3-L7) -> 42 | N7: 814 | O7: 429 | P7: 46282 | Q7: =IF(P7="","",'Read me'!$B$3-P7) -> 18 | R7: US-style DTC funnel targeting Ireland; prices in USD.
A8: 4 | B8: Holland & Barrett (IE) | C8: https://www.hollandandbarrett.ie | D8: Open Ad Library | E8: Health store chain: vitamins, own-label gummies (women's multi, creatine) | F8: Yes (own-label gummies) | G8: 3-for-2 mix & match item | H8: 27.94 | I8: EUR | J8: =IF(H8="","",H8*INDEX(FX!$B$5:$B$8,MATCH(I8,FX!$A$5:$A$8,0))) -> 27.94 | K8: 20% off €45 / 15% off €35; Buy 1 get 1 half price; 3 for 2; 20% off first order | L8: 45931 | M8: =IF(L8="","",'Read me'!$B$3-L8) -> 369 | N8: 552 | O8: 38 | P8: 46239 | Q8: =IF(P8="","",'Read me'!$B$3-P8) -> 61
A9: 5 | B9: MacLir | C9: https://maclir.co | D9: Open Ad Library | E9: Creatine gummies | F9: Yes – gummies only | G9: Creatine gummies, 1 month (subscription) | H9: 34 | I9: EUR | J9: =IF(H9="","",H9*INDEX(FX!$B$5:$B$8,MATCH(I9,FX!$A$5:$A$8,0))) -> 34 | K9: 52% OFF sale; 2 months + 1 free; free shipping with subscription; 30-day money-back (one-time 40 €) | L9: 45928 | M9: =IF(L9="","",'Read me'!$B$3-L9) -> 372 | N9: 412 | O9: 89 | P9: 46215 | Q9: =IF(P9="","",'Read me'!$B$3-P9) -> 85
A10: 6 | B10: Vegetology | C10: https://www.vegetology.com | D10: Open Ad Library | E10: Vegan vitamins (tablets, bundles), UK brand | F10: No (tablets) | G10: Vegan Mind & Memory bundle (60 days) | H10: 60 | I10: GBP | J10: =IF(H10="","",H10*INDEX(FX!$B$5:$B$8,MATCH(I10,FX!$A$5:$A$8,0))) -> 70.2 | K10: Bundles; free shipping over £70 | L10: 44923 | M10: =IF(L10="","",'Read me'!$B$3-L10) -> 1377 | N10: 263 | O10: 71 | P10: 45499 | Q10: =IF(P10="","",'Read me'!$B$3-P10) -> 801 | R10: UK store, prices in GBP.
A11: 7 | B11: Igennus Healthcare Nutrition | C11: https://igennus.com | D11: Open Ad Library | E11: Omega-3 & B-vitamin supplements (UK) | F11: No | I11: EUR | J11: =IF(H11="","",H11*INDEX(FX!$B$5:$B$8,MATCH(I11,FX!$A$5:$A$8,0))) | K11: Free 15-min nutrition consult | L11: 45967 | M11: =IF(L11="","",'Read me'!$B$3-L11) -> 333 | N11: 192 | O11: 18 | P11: 46154 | Q11: =IF(P11="","",'Read me'!$B$3-P11) -> 146
A12: 8 | B12: Whole World Botanicals | C12: https://wholeworldbotanicals.com | D12: Open Ad Library | E12: Maca & botanical supplements (US) | F12: No | I12: EUR | J12: =IF(H12="","",H12*INDEX(FX!$B$5:$B$8,MATCH(I12,FX!$A$5:$A$8,0))) | K12: 15% off first order + free Maca guide | L12: 45937 | M12: =IF(L12="","",'Read me'!$B$3-L12) -> 363 | N12: 33 | O12: 4 | P12: 46064 | Q12: =IF(P12="","",'Read me'!$B$3-P12) -> 236 | R12: US store prices in USD.

Sheet Austria
A1: Austria – stores selling gummies / supplements with Meta ads
A2: 9 stores · Meta data collected on the date in 'Read me'!B3 · sorted by number of ads
A4: # | B4: Store | C4: Store link | D4: Meta Ad Library link | E4: What they sell | F4: Sells gummies? | G4: Entry product | H4: Entry price (local) | I4: Currency | J4: Entry price (EUR) | K4: Offer | L4: Oldest ad in Ad Library (active or not) | M4: Days since oldest ad | N4: Ads in Ad Library (total) | O4: Active ads now | P4: Oldest live ad: start date | Q4: Days since oldest live ad | R4: Notes
A5: 1 | B5: Bears with Benefits | C5: https://www.bears-with-benefits.com | D5: Open Ad Library | E5: Vitamin gummy bears (hair, PMS, sleep, shape…) | F5: Yes – gummies only | G5: Promo bundle (from) | H5: 49.9 | I5: EUR | J5: =IF(H5="","",H5*INDEX(FX!$B$5:$B$8,MATCH(I5,FX!$A$5:$A$8,0))) -> 49.9 | K5: Promo sets up to −24%; free shipping in DE & AT from 49 € | L5: 44166 | M5: =IF(L5="","",'Read me'!$B$3-L5) -> 2134 | N5: 2693 | O5: 218 | P5: 46034 | Q5: =IF(P5="","",'Read me'!$B$3-P5) -> 266 | R5: Same page as Germany.
A6: 2 | B6: TISSO Naturprodukte | C6: https://www.tisso.de | D6: Open Ad Library | E6: Natural supplements (gut, vitamins), German practice brand | F6: No | G6: Vitamin product (from) | H6: 33.95 | I6: EUR | J6: =IF(H6="","",H6*INDEX(FX!$B$5:$B$8,MATCH(I6,FX!$A$5:$A$8,0))) -> 33.95 | K6: Product packages up to −20%; 5.50 € welcome discount | L6: 45694 | M6: =IF(L6="","",'Read me'!$B$3-L6) -> 606 | N6: 2078 | O6: 265 | P6: 46048 | Q6: =IF(P6="","",'Read me'!$B$3-P6) -> 252
A7: 3 | B7: Vitafant | C7: https://vitafant.com | D7: Open Ad Library | E7: Greens powders & supplements | F7: No (powders) | G7: Grüne Helfer powder (advertised) | H7: 39.9 | I7: EUR | J7: =IF(H7="","",H7*INDEX(FX!$B$5:$B$8,MATCH(I7,FX!$A$5:$A$8,0))) -> 39.9 | K7: 6-pack −15%; 10% newsletter code; free shipping from 50 € | L7: 45847 | M7: =IF(L7="","",'Read me'!$B$3-L7) -> 453 | N7: 1407 | O7: 244 | P7: 45932 | Q7: =IF(P7="","",'Read me'!$B$3-P7) -> 368
A8: 4 | B8: Pure Encapsulations AT&DE | C8: https://www.purecaps.net | D8: Open Ad Library | E8: Hypoallergenic premium supplements (capsules, drops) | F8: No | G8: Vitamin C 1000 buffered, 30 caps (from) | H8: 17.8 | I8: EUR | J8: =IF(H8="","",H8*INDEX(FX!$B$5:$B$8,MATCH(I8,FX!$A$5:$A$8,0))) -> 17.8 | K8: Discount conditions on site; free shipping to Austria over a threshold | L8: 45469 | M8: =IF(L8="","",'Read me'!$B$3-L8) -> 831 | N8: 1065 | O8: 390 | P8: 45558 | Q8: =IF(P8="","",'Read me'!$B$3-P8) -> 742
A9: 5 | B9: Bare Body Wellness | C9: https://www.bellunova.com/1001-mx-vir/adv | D9: Open Ad Library | E9: Advertorial funnels for women's supplements (Virelle, Oravelle) | F9: No | I9: EUR | J9: =IF(H9="","",H9*INDEX(FX!$B$5:$B$8,MATCH(I9,FX!$A$5:$A$8,0))) | L9: 46198 | M9: =IF(L9="","",'Read me'!$B$3-L9) -> 102 | N9: 475 | O9: 45 | P9: 46295 | Q9: =IF(P9="","",'Read me'!$B$3-P9) -> 5 | R9: Not a classic store: ads lead to advertorial pages on rotating domains.
A10: 6 | B10: FormMed HealthCare | C10: https://formmed.de | D10: Open Ad Library | E10: Premium micronutrients (German) | F10: No (capsules) | G10: Homocyst-in-form (advertised), 30 days | H10: 19.9 | I10: EUR | J10: =IF(H10="","",H10*INDEX(FX!$B$5:$B$8,MATCH(I10,FX!$A$5:$A$8,0))) -> 19.9 | K10: 10% off next order; free shipping from 50 € | L10: 45814 | M10: =IF(L10="","",'Read me'!$B$3-L10) -> 486 | N10: 376 | O10: 115 | P10: 46203 | Q10: =IF(P10="","",'Read me'!$B$3-P10) -> 97
A11: 7 | B11: VitaePro Österreich | C11: https://www.vitaepro.at | D11: Open Ad Library | E11: Joint & muscle supplement (astaxanthin) via subscription | F11: No (capsules) | G11: First pack (trial) | H11: 9.95 | I11: EUR | J11: =IF(H11="","",H11*INDEX(FX!$B$5:$B$8,MATCH(I11,FX!$A$5:$A$8,0))) -> 9.95 | K11: First pack for 9.95 € then subscription (cancel anytime) | L11: 45930 | M11: =IF(L11="","",'Read me'!$B$3-L11) -> 370 | N11: 345 | O11: 55 | P11: 46204 | Q11: =IF(P11="","",'Read me'!$B$3-P11) -> 96
A12: 8 | B12: Forte Natura Gummies | C12: https://de.forte-natura.com | D12: Open Ad Library | E12: Gummies: colostrum, joints, sleep (German-language DTC) | F12: Yes – gummies only | G12: Colostrum Forte gummies (monthly price) | H12: 29 | I12: EUR | J12: =IF(H12="","",H12*INDEX(FX!$B$5:$B$8,MATCH(I12,FX!$A$5:$A$8,0))) -> 29 | K12: 3- and 6-pack savings bundles; free premium DHL shipping; free Sleep gummies with joint bundle | L12: 46096 | M12: =IF(L12="","",'Read me'!$B$3-L12) -> 204 | N12: 111 | O12: 11 | P12: 46300 | Q12: =IF(P12="","",'Read me'!$B$3-P12) -> 0
A13: 9 | B13: Supradyn Österreich | C13: https://www.supradyn.at | D13: Open Ad Library | E13: Bayer multivitamins (tablets, gummies) – sold via pharmacies | F13: Some (Supradyn gummies) | I13: EUR | J13: =IF(H13="","",H13*INDEX(FX!$B$5:$B$8,MATCH(I13,FX!$A$5:$A$8,0))) | L13: 45931 | M13: =IF(L13="","",'Read me'!$B$3-L13) -> 369 | N13: 30 | O13: 13 | P13: 46176 | Q13: =IF(P13="","",'Read me'!$B$3-P13) -> 124 | R13: Brand site has no shop; sold in pharmacies/drugstores.
