Workbook

Sheet Summary
A1: Moroccan gummy & supplement stores on Meta: summary
A2: ="Research date: "&TEXT('Notes & method'!B3,"yyyy-mm-dd") -> Research date: 2026-10-04
A3: Key figures
A4: Stores tracked | B4: =COUNTA(Stores!$B$2:$B$34) -> 33
A5: Stores selling gummies | B5: =COUNTIF(Stores!$D$2:$D$34,"Yes*") -> 9
A6: Average entry price (MAD) | B6: =AVERAGE(Stores!$G$2:$G$34) -> 186.2
A7: Median entry price (MAD) | B7: =MEDIAN(Stores!$G$2:$G$34) -> 190
A8: Lowest entry price (MAD) | B8: =MIN(Stores!$G$2:$G$34) -> 69
A9: Highest entry price (MAD) | B9: =MAX(Stores!$G$2:$G$34) -> 319
A10: Total ads in Ad Library (Morocco) | B10: =SUM(Stores!$Q$2:$Q$34) -> 2524
A11: Average ads per store | B11: =AVERAGE(Stores!$Q$2:$Q$34) -> 76.484848
A12: Average days since oldest live ad | B12: =AVERAGE(Stores!$P$2:$P$34) -> 155.0303
A14: Store language (website) | B14: Stores
A15: French only | B15: =COUNTIF(Stores!$L$2:$L$34,"French") -> 16
A16: Arabic only (incl. Darija) | B16: =COUNTIF(Stores!$L$2:$L$34,"Arabic")+COUNTIF(Stores!$L$2:$L$34,"Arabic (Darija)") -> 5
A17: Bilingual (French + Arabic) | B17: =COUNTIF(Stores!$L$2:$L$34,"*+*") -> 8
A18: No website (WhatsApp / Instagram) | B18: =COUNTIF(Stores!$L$2:$L$34,"No website*") -> 4
A21: Top 10 by ads in Ad Library | B21: Ads (Morocco) | C21: Oldest live ad
A22: =IF(Stores!Q2="","",Stores!B2) -> Argivit Maroc (Argivitmaroc.official) | B22: =IF(Stores!Q2="","",Stores!Q2) -> 639 | C22: =IF(Stores!N2="","",Stores!N2) -> 46225
A23: =IF(Stores!Q3="","",Stores!B3) -> Argivit.com (2nd page) | B23: =IF(Stores!Q3="","",Stores!Q3) -> 352 | C23: =IF(Stores!N3="","",Stores!N3) -> 46248
A24: =IF(Stores!Q4="","",Stores!B4) -> Dr. Pops | B24: =IF(Stores!Q4="","",Stores!Q4) -> 246 | C24: =IF(Stores!N4="","",Stores!N4) -> 46288
A25: =IF(Stores!Q5="","",Stores!B5) -> Kivra | B25: =IF(Stores!Q5="","",Stores!Q5) -> 204 | C25: =IF(Stores!N5="","",Stores!N5) -> 46044
A26: =IF(Stores!Q6="","",Stores!B6) -> Capila | B26: =IF(Stores!Q6="","",Stores!Q6) -> 163 | C26: =IF(Stores!N6="","",Stores!N6) -> 45730
A27: =IF(Stores!Q7="","",Stores!B7) -> Toltna | B27: =IF(Stores!Q7="","",Stores!Q7) -> 151 | C27: =IF(Stores!N7="","",Stores!N7) -> 46277
A28: =IF(Stores!Q8="","",Stores!B8) -> HARD Morocco | B28: =IF(Stores!Q8="","",Stores!Q8) -> 145 | C28: =IF(Stores!N8="","",Stores!N8) -> 46246
A29: =IF(Stores!Q9="","",Stores!B9) -> Naturea Maroc | B29: =IF(Stores!Q9="","",Stores!Q9) -> 105 | C29: =IF(Stores!N9="","",Stores!N9) -> 46267
A30: =IF(Stores!Q10="","",Stores!B10) -> Gleamy | B30: =IF(Stores!Q10="","",Stores!Q10) -> 65 | C30: =IF(Stores!N10="","",Stores!N10) -> 45616
A31: =IF(Stores!Q11="","",Stores!B11) -> Melixir | B31: =IF(Stores!Q11="","",Stores!Q11) -> 60 | C31: =IF(Stores!N11="","",Stores!N11) -> 46075
A33: Note: "Oldest live ad" is the oldest ad still running (Meta deletes stopped ads for Moroccan advertisers). See "Notes & method".

Sheet Stores
A1: # | B1: Store | C1: Category | D1: Sells gummies? | E1: Website | F1: Main products | G1: Entry price (MAD) | H1: Entry product | I1: Offer on website | J1: Promos seen in ads | K1: Delivery / payment (ads) | L1: Store language (website) | M1: Platform | N1: Oldest live ad: start date | O1: Status of that ad | P1: Days since oldest live ad | Q1: Ads in Ad Library (Morocco) | R1: Newest ad: start date | S1: Oldest product on store | T1: Domain registered | U1: Page likes | V1: Ad Library link | W1: Facebook page | X1: Ad landing domains
A2: 1 | B2: Argivit Maroc (Argivitmaroc.official) | C2: Kids growth supplements brand | D2: Yes | E2: argivitmaroc.com | F2: Kids/teen growth multivitamins (L-arginine + vit D): Argivit Classic, Focus, Gummies | G2: 299 | H2: Argivit Gummies | I2: Classic 399 (was 499-549), Focus 450 (was 649); Discovery pack 3 products 599 MAD; ads push '-50% limited time' | J2: -50% | K2: Cash on delivery | L2: French + Arabic | M2: Shopify | N2: 46225 | O2: Active | P2: =IF(N2="","",'Notes & method'!$B$3-N2) -> 74 | Q2: 639 | R2: 46298 | S2: 45867 | T2: 45915 | U2: 277 | V2: Open Ad Library | W2: Facebook page | X2: argivitmaroc.com, instagram.com
A3: 2 | B3: Argivit.com (2nd page) | C3: Kids growth supplements brand | D3: Yes | E3: argivitmaroc.com | F3: Same brand as Argivit Maroc (second Facebook page) | G3: 299 | H3: Argivit Gummies | I3: Same as Argivit Maroc | J3: -50% | K3: Cash on delivery | L3: French + Arabic | M3: Shopify | N3: 46248 | O3: Active | P3: =IF(N3="","",'Notes & method'!$B$3-N3) -> 51 | Q3: 352 | R3: 46298 | S3: 45867 | T3: 45915 | U3: 173 | V3: Open Ad Library | W3: Facebook page | X3: api.whatsapp.com, argivitmaroc.com
A4: 3 | B4: Dr. Pops | C4: Wellness lollipops (honey/propolis) | D4: No (lollipops) | E4: drpops.ma | F4: Honey & propolis lollipops for kids/adults, goat-milk caramel | G4: 199 | H4: Propolis lollipops | I4: No discount shown | J4: -40% | L4: French | M4: Shopify | N4: 46288 | O4: Active | P4: =IF(N4="","",'Notes & method'!$B$3-N4) -> 11 | Q4: 246 | R4: 46293 | S4: 46288 | U4: 61 | V4: Open Ad Library | W4: Facebook page | X4: drpops.ma
A5: 4 | B5: Kivra | C5: Supplements brand | D5: No | E5: kivra.ma | F5: KivraBloom, BioSliim (slimming), BioSSITOL (inositol), KivraMAX Collagen | G5: 199 | H5: Any product (was 299) | I5: -33% on all products (299 -> 199 MAD) | K5: Cash on delivery, Free delivery | L5: Arabic | M5: YouCan | N5: 46044 | O5: Inactive | P5: =IF(N5="","",'Notes & method'!$B$3-N5) -> 255 | Q5: 204 | R5: 46292 | U5: 1057 | V5: Open Ad Library | W5: Facebook page | X5: kivra.ma, api.whatsapp.com
A6: 5 | B6: Capila | C6: Hair care + hair supplement brand (also in pharmacies) | D6: No | E6: capila.ma | F6: Anti hair-loss capsules, shampoo, serum, lotion | G6: 174 | H6: Capila hair supplement 60 caps | I6: 3-in-1 hair range 249 (was 450-498) | L6: French | M6: Shopify | N6: 45730 | O6: Inactive | P6: =IF(N6="","",'Notes & method'!$B$3-N6) -> 569 | Q6: 163 | R6: 46249 | S6: 45694 | U6: 16681 | V6: Open Ad Library | W6: Facebook page | X6: capila.ma
A7: 6 | B7: Toltna | C7: Single-product supplement (height growth) | D7: No | E7: toltna.com | F7: Toltna+ growth supplement | G7: 319 | H7: Toltna+ | I7: No discount shown on site | L7: Arabic (Darija) | M7: Shopify | N7: 46277 | O7: Active | P7: =IF(N7="","",'Notes & method'!$B$3-N7) -> 22 | Q7: 151 | R7: 46296 | S7: 46163 | T7: 46144 | U7: 6642 | V7: Open Ad Library | W7: Facebook page | X7: toltna.com, instagram.com
A8: 7 | B8: HARD Morocco | C8: Gummies & supplements brand | D8: Yes | E8: hard.ma | F8: Ashwagandha, energy, hair & nails gummies; shilajit, collagen, melatonin, fat burner, testosterone booster, omega 3, zinc, vit C | G8: 95 | H8: Vitamin C 30 caps (gummies from 275 MAD) | I8: 2 + 1 free (500 MAD) on collagen, melatonin, fat burner; gummies 1/2/3 months = 280/395/500 MAD; Full Pack 3 gummies 480 MAD; crossed-out prices up to -58% | K8: Free delivery | L8: French | M8: Shopify | N8: 46246 | O8: Active | P8: =IF(N8="","",'Notes & method'!$B$3-N8) -> 53 | Q8: 145 | R8: 46291 | S8: 45641 | U8: 57 | V8: Open Ad Library | W8: Facebook page | X8: hard.ma
A9: 8 | B9: Naturea Maroc | C9: Supplements brand (moringa) | D9: No | E9: natureamaroc.com | F9: Moringa / moringa-curcuma capsules (vitality, digestion, prostate) | G9: 239 | H9: Moringa Curcuma 30 caps | I9: Ads: cure 2 + 1 free at 339 DH with free delivery, cash on delivery | J9: 2+1 free | K9: Cash on delivery, Free delivery | L9: French | M9: Shopify | N9: 46267 | O9: Active | P9: =IF(N9="","",'Notes & method'!$B$3-N9) -> 32 | Q9: 105 | R9: 46293 | T9: 46215 | U9: 424 | V9: Open Ad Library | W9: Facebook page | X9: natureamaroc.com
A10: 9 | B10: Gleamy | C10: Beauty + supplements brand | D10: No | E10: gleamy.ma | F10: Super Collagen, liposomal iron, melatonin, propolis, skin-lightening cure + skincare | G10: 199 | H10: Super Collagen / Liposomal Iron, 1 month | I10: 1/2/3 boxes = 199/398/499 MAD; 'Fer 3 + 1' promo 597 MAD; 3-month collagen + free honey soap 499 MAD | K10: Free delivery | L10: French + Arabic | M10: Shopify | N10: 45616 | O10: Active | P10: =IF(N10="","",'Notes & method'!$B$3-N10) -> 683 | Q10: 65 | R10: 46295 | U10: 27602 | V10: Open Ad Library | W10: Facebook page | X10: gleamy.ma, mygleamy.ma
A11: 10 | B11: Melixir | C11: Single-product supplement store | D11: No | E11: melixir.shop | F11: Magnesium complex | G11: 239 | H11: Magnesium Complex | I11: No discount shown | J11: 2+1 free | K11: Cash on delivery | L11: French | M11: Shopify | N11: 46075 | O11: Active | P11: =IF(N11="","",'Notes & method'!$B$3-N11) -> 224 | Q11: 60 | R11: 46291 | S11: 46062 | T11: 46062 | U11: 1168 | V11: Open Ad Library | W11: Facebook page | X11: melixir.shop
A12: 11 | B12: Vitamiam | C12: Gummies store | D12: Yes | E12: vitamiam.shop | F12: Shilajit, mushroom, collagen, feminine/intimate, melatonin, ashwagandha, ACV gummies (incl. Goli) | G12: 229 | H12: Goli melatonin / ashwagandha / ACV gummies (was 270) | I12: Crossed-out prices: shilajit 239-259 (was 300-350), feminine 239 (was 450); slimming & energy pack 259 (was 399) | J12: -40% | K12: Cash on delivery, Free delivery | L12: French | M12: Shopify | N12: 46188 | O12: Active | P12: =IF(N12="","",'Notes & method'!$B$3-N12) -> 111 | Q12: 58 | R12: 46290 | S12: 45903 | T12: 45847 | U12: 580 | V12: Open Ad Library | W12: Facebook page | X12: vitamiam.shop
A13: 12 | B13: Simo Life (BeTheOne) | C13: Supplements brand | D13: No | E13: betheone.shop | F13: Be Motivated, Be The Man, Be Strong, Be Genius (influencer Simo Life's Page, 855k likes) | G13: 190 | H13: Be Motivated (was 290) | I13: Free delivery + cash on delivery; up to -60% claims | L13: Arabic | M13: YouCan | N13: 45362 | O13: Active | P13: =IF(N13="","",'Notes & method'!$B$3-N13) -> 937 | Q13: 49 | R13: 46292 | T13: 44936 | U13: 854596 | V13: Open Ad Library | W13: Facebook page | X13: betheone.shop, lmofidacademy.com
A14: 13 | B14: Hoojan | C14: Health & beauty marketplace | D14: Yes (brands) | E14: hoojan.com | F14: Marketplace: supplements, whey, beauty, sport | H14: Marketplace (many brands); site blocks bots | I14: Ads: Performance pack (whey + creatine + multivitamins + shaker) 1,499 DH, save 150 DH; same-day delivery Casablanca & Rabat | L14: French + Arabic | M14: Custom | N14: 46290 | O14: Active | P14: =IF(N14="","",'Notes & method'!$B$3-N14) -> 9 | Q14: 43 | R14: 46297 | T14: 44883 | U14: 4410 | V14: Open Ad Library | W14: Facebook page | X14: hoojan.com
A15: 14 | B15: Zorya Labs | C15: Gummies brand | D15: Yes | E15: zoryalab.com | F15: Energy Focus, Stress Balance, Night Reset gummies (ads run from a repurposed personal Page with 153k likes) | G15: 289 | H15: Energy Focus / Stress Balance gummies, 30-day | I15: 60 days 520 / 90 days 737 MAD; 2-product packs 539-549 (was 578-588); full ritual 799 (was 877) | K15: Cash on delivery | L15: French | M15: Shopify | N15: 46261 | O15: Active | P15: =IF(N15="","",'Notes & method'!$B$3-N15) -> 38 | Q15: 39 | R15: 46294 | S15: 46207 | T15: 46147 | U15: 153063 | V15: Open Ad Library | W15: Facebook page | X15: zoryalab.com
A16: 15 | B16: Menopause Support Plus | C16: Supplement (WhatsApp seller) | D16: No | F16: Menopause support supplement | H16: Price given on WhatsApp | I16: Delivery all Morocco, cash on delivery | K16: Cash on delivery | L16: No website (WhatsApp) | M16: WhatsApp | N16: 46274 | O16: Active | P16: =IF(N16="","",'Notes & method'!$B$3-N16) -> 25 | Q16: 38 | R16: 46295 | U16: 452 | V16: Open Ad Library | W16: Facebook page | X16: api.whatsapp.com
A17: 16 | B17: Maghreb Nutrition | C17: Sports nutrition (official distributor) | D17: No | E17: maghrebnutrition.ma | F17: Whey, creatine, collagen, endurance | H17: Site blocks bots (Cloudflare) | K17: Free delivery | L17: French | M17: Unknown | N17: 46091 | O17: Active | P17: =IF(N17="","",'Notes & method'!$B$3-N17) -> 208 | Q17: 36 | R17: 46293 | U17: 14572 | V17: Open Ad Library | W17: Facebook page | X17: maghrebnutrition.ma
A18: 17 | B18: Ferilys | C18: Supplements brand (women) | D18: No | E18: ferilys.com | F18: Liposomal iron, magnesium bisglycinate, saffron, energy & beauty boost + skincare | G18: 150 | H18: Magnesium bisglycinate (149.99) | I18: 1/2/3 boxes: iron 199/349/449; cures 449-499 (was 698-749) | J18: -30% | K18: Free delivery | L18: French | M18: Shopify | N18: 46029 | O18: Active | P18: =IF(N18="","",'Notes & method'!$B$3-N18) -> 270 | Q18: 20 | R18: 46282 | S18: 45966 | T18: 45959 | U18: 1604 | V18: Open Ad Library | W18: Facebook page | X18: ferilys.com, instagram.com
A19: 18 | B19: Detox360 | C19: Single-product supplement (detox) | D19: No | E19: snqkpu-w0.myshopify.com | F19: Detox360 30-day cure | G19: 199 | H19: 30-day cure (was 299) | I19: -33% (299 -> 199 MAD) | K19: Cash on delivery, Free delivery | L19: Arabic | M19: Shopify | N19: 46264 | O19: Active | P19: =IF(N19="","",'Notes & method'!$B$3-N19) -> 35 | Q19: 19 | R19: 46294 | S19: 46263 | U19: 134 | V19: Open Ad Library | W19: Facebook page | X19: snqkpu-w0.myshopify.com
A20: 19 | B20: Body Flex | C20: Fitness supplements | D20: No | E20: body-flex.shop | F20: Testo booster, multivitamin, protein | G20: 120 | H20: Testo booster | I20: Pack 229 MAD (was 836); protein 189 (was 349) | K20: Cash on delivery | L20: Arabic + French | M20: Shopify | N20: 46223 | O20: Active | P20: =IF(N20="","",'Notes & method'!$B$3-N20) -> 76 | Q20: 18 | R20: 46272 | S20: 45981 | T20: 45986 | U20: 2337 | V20: Open Ad Library | W20: Facebook page | X20: body-flex.shop
A21: 20 | B21: Laprot Nutrition | C21: Sports nutrition store | D21: No | E21: laprot.com | F21: Whey, creatine, pre-workout, vitamins, magnesium | G21: 155 | H21: Zinc picolinate 30 caps (pre-workout shots from 25) | I21: 69 of 95 products discounted | K21: Cash on delivery, Free delivery | L21: French | M21: WooCommerce | N21: 45938 | O21: Active | P21: =IF(N21="","",'Notes & method'!$B$3-N21) -> 361 | Q21: 16 | R21: 46285 | T21: 44951 | U21: 7441 | V21: Open Ad Library | W21: Facebook page | X21: laprot.com, api.whatsapp.com
A22: 21 | B22: Côté Vert (Revoxine) | C22: Supplements store | D22: No | E22: revoxine.ma | F22: Shilajit, berberine, biotin, D3, probiotics, melatonin, glutathione, zinc... | G22: 159 | H22: Vit E / zinc / liver detox | I22: Crossed-out prices on all items (e.g. shilajit 179, was 269); ads: magnesium glycinate 159 DH instead of 199 | J22: -20% | K22: Cash on delivery, Free delivery | L22: French | M22: Shopify | N22: 46283 | O22: Active | P22: =IF(N22="","",'Notes & method'!$B$3-N22) -> 16 | Q22: 10 | R22: 46295 | S22: 45984 | U22: 2109 | V22: Open Ad Library | W22: Facebook page | X22: revoxine.ma
A23: 22 | B23: Elev8 Supplements | C23: Supplements brand | D23: Yes | E23: elev8supplements.ma | F23: Hair/nails/skin gummies, magnesium bisglycinate, melatonin, multivitamins, omega 3 | G23: 180 | H23: Melatonin (153 MAD with subscription) | I23: -15% on monthly subscription; packs Sommeil 513, Vitalité 615, Beauté 720 MAD (-15%); free delivery from 499 MAD | L23: French | M23: WooCommerce | N23: 46219 | O23: Active | P23: =IF(N23="","",'Notes & method'!$B$3-N23) -> 80 | Q23: 8 | R23: 46293 | U23: 165 | V23: Open Ad Library | W23: Facebook page | X23: elev8supplements.ma, instagram.com
A24: 23 | B24: VitalisPro | C24: Supplements store | D24: No | E24: vitalispro.online | F24: Moringa, berberine, chromium, collagen, spirulina, slimming packs | G24: 95 | H24: Moringa 60 tabs (was 250) | I24: Heavy crossed-out prices; packs 190-300 MAD (was 250-710) | K24: Cash on delivery | L24: Arabic + French | M24: WooCommerce | N24: 46287 | O24: Active | P24: =IF(N24="","",'Notes & method'!$B$3-N24) -> 12 | Q24: 7 | R24: 46298 | T24: 45530 | U24: 3914 | V24: Open Ad Library | W24: Facebook page | X24: api.whatsapp.com, vitalispro.online
A25: 24 | B25: Mapara.ma | C25: Online parapharmacy (ads mostly hair care) | D25: Yes (brands) | E25: mapara.ma | F25: Parapharmacy incl. supplements | H25: Site blocked by Cloudflare | J25: -40% | K25: Cash on delivery | L25: French | M25: Unknown | N25: 46129 | O25: Active | P25: =IF(N25="","",'Notes & method'!$B$3-N25) -> 170 | Q25: 7 | R25: 46268 | U25: 273 | V25: Open Ad Library | W25: Facebook page | X25: mapara.ma
A26: 25 | B26: Nutrifio Maroc | C26: Supplements brand | D26: No | F26: Collagen + vitamins + hyaluronic acid + zinc routine | H26: Orders via Instagram | L26: No website (Instagram) | M26: Instagram | N26: 46200 | O26: Active | P26: =IF(N26="","",'Notes & method'!$B$3-N26) -> 99 | Q26: 4 | R26: 46201 | U26: 404 | V26: Open Ad Library | W26: Facebook page | X26: instagram.com
A27: 26 | B27: Muscle Fuel Maroc | C27: Sports nutrition (physical shop, Rabat) | D27: ? | F27: Imported sports supplements | H27: Shop in Rabat (Bab Bouiba mall) / Instagram | I27: 'Strongest offers' in ads, no prices | L27: No website (Instagram) | M27: Instagram | N27: 46293 | O27: Active | P27: =IF(N27="","",'Notes & method'!$B$3-N27) -> 6 | Q27: 4 | R27: 46296 | U27: 3615 | V27: Open Ad Library | W27: Facebook page | X27: instagram.com
A28: 27 | B28: AlphaVital | C28: Supplements store | D28: No | E28: alphavital.ma | F28: Berberine, collagen, magnesium, D3+K2, iron, saw palmetto, bundles | G28: 69 | H28: Saw Palmetto (was 150) | I28: 82 of 100 products discounted; 2-product bundles 199-299 MAD; free delivery from 170 DH (ads) | K28: Free delivery | L28: French + Arabic | M28: WooCommerce | N28: 46242 | O28: Active | P28: =IF(N28="","",'Notes & method'!$B$3-N28) -> 57 | Q28: 3 | R28: 46244 | U28: 8793 | V28: Open Ad Library | W28: Facebook page | X28: alphavital.ma
A29: 28 | B29: Maroc Vitamin | C29: Imported supplements store | D29: Few | E29: marocvita.com | F29: Imported vitamins (Now, Solgar-type), probiotics, collagen, omega 3, creatine | G29: 82 | H29: MGD Vigne Rouge 90 caps (was 120) | I29: All listed products show a crossed-out price (about -10 to -30%); ads: CollagenUP 330 DH instead of 440 (-25%); delivery 20 DH Casablanca / 30 DH other cities, cash on delivery | J29: -25% | K29: Cash on delivery, Free delivery | L29: French | M29: WooCommerce | N29: 45904 | O29: Active | P29: =IF(N29="","",'Notes & method'!$B$3-N29) -> 395 | Q29: 3 | R29: 46292 | T29: 45201 | U29: 2245 | V29: Open Ad Library | W29: Facebook page | X29: marocvita.com, api.whatsapp.com
A30: 29 | B30: Supplements Maroc | C30: Sports nutrition + vitamins store | D30: No | E30: supplementsmaroc.com | F30: Imported vitamins, creatine, whey, bars, accessories | G30: 99 | H30: Vitamin B complex 100 tabs (was 249) | I30: 379 of 486 products discounted | L30: Arabic + French | M30: Shopify | N30: 46179 | O30: Active | P30: =IF(N30="","",'Notes & method'!$B$3-N30) -> 120 | Q30: 3 | R30: 46232 | S30: 44094 | T30: 44302 | U30: 21474 | V30: Open Ad Library | W30: Facebook page | X30: supplementsmaroc.com
A31: 30 | B31: Vitamin Store Maroc | C31: Sports nutrition + vitamins (retail & wholesale) | D31: ? | F31: Protein, vitamins & minerals, creatine, amino acids, gainers | H31: Orders via Instagram | I31: Wholesale and retail | L31: No website (Instagram) | M31: Instagram | N31: 46295 | O31: Active | P31: =IF(N31="","",'Notes & method'!$B$3-N31) -> 4 | Q31: 3 | R31: 46299 | U31: 42 | V31: Open Ad Library | W31: Facebook page | X31: instagram.com
A32: 31 | B32: VertuPlus | C32: Supplements brand (capsules + gummies) | D32: Yes | E32: vertuplus.ma | F32: Multivitamins, magnesium, vitamin C, D3+K2, Kids+, spirulina, marine collagen, moringa, turmeric | H32: No prices online (catalogue site) | I32: Free delivery from 399 MAD; 30-day money-back guarantee; brand says it is 10 years old (giveaway ad) | L32: French | M32: WordPress (catalogue) | N32: 46193 | O32: Active | P32: =IF(N32="","",'Notes & method'!$B$3-N32) -> 106 | Q32: 3 | R32: 46204 | U32: 1456 | V32: Open Ad Library | W32: Facebook page | X32: instagram.com
A33: 32 | B33: Atlas Pure | C33: Herbal products (mostly creams; ads push vitiligo cream; sells joint capsules) | D33: No | E33: atlaspure.shop | F33: Joint capsules, hair serum, breath drops, foot spray, vitiligo cream | G33: 249 | H33: Joint capsules | I33: Free delivery, cash on delivery, 30-day money-back guarantee | K33: Cash on delivery, Free delivery | L33: Arabic (Darija) | M33: Custom | N33: 46294 | O33: Active | P33: =IF(N33="","",'Notes & method'!$B$3-N33) -> 5 | Q33: 2 | R33: 46296 | U33: 10024 | V33: Open Ad Library | W33: Facebook page | X33: atlaspure.shop
A34: 33 | B34: Dr Nutri | C34: Imported supplements store | D34: No | E34: drnutri.ma | F34: Imported vitamins: D3, B complex, collagen, berberine, magnesium, NAC, zinc | G34: 129 | H34: Vitamin D3 / B complex | I34: Some crossed-out prices (e.g. collagen 349, was 450); fast delivery all Morocco | L34: French | M34: YouCan | N34: 46297 | O34: Active | P34: =IF(N34="","",'Notes & method'!$B$3-N34) -> 2 | Q34: 1 | R34: 46297 | U34: 88 | V34: Open Ad Library | W34: Facebook page | X34: drnutri.ma

Sheet Notes & method
A1: Moroccan gummy & supplement stores: Meta ad research
A3: Research date | B3: 46299 | C3: Change this date to refresh the "Days since oldest live ad" column.
A5: What each column means
A6: Entry price (MAD) | B6: Cheapest single supplement on the store website (1 unit / 1-month cure), in dirhams. Bundles and crossed-out prices are in "Offer on website".
A7: Offer on website | B7: Discounts, bundles (2+1, 1/2/3 months), packs and crossed-out prices seen on the store site on the research date.
A8: Promos seen in ads | B8: Discount percentages and N+N offers found in the text of the ads sampled from the Ad Library.
A9: Delivery / payment (ads) | B9: Cash on delivery / free delivery claims found in ad text.
A10: Store language (website) | B10: Main language of the store website (homepage + product page), not of the ads. Darija = Moroccan Arabic.
A11: Oldest live ad: start date | B11: Start date of the oldest ad the Meta Ad Library shows for this Page (country = Morocco). IMPORTANT: outside the EU, Meta only keeps non-political ads while they are running. Stopped ads disappear, so this is the oldest ad that is STILL RUNNING. It is not the first ad the store ever ran. Use "Oldest product on store" and "Domain registered" as extra clues to when the store started. For the Facebook Page creation date, open the Ad Library link and click "About" (Page transparency): Meta rate-limited that field during this research, so it could not be collected automatically.
A12: Status of that ad | B12: Whether that oldest ad is still active. Most are Active, for the reason above. A few stopped ads still show (e.g. Kivra, Capila), so those stores have been advertising at least since that date.
A13: Days since oldest live ad | B13: Formula: research date (cell B3) minus the oldest live ad date.
A14: Ads in Ad Library (Morocco) | B14: Number of results the Ad Library reports for the Page with country = Morocco and status = all. Meta shows this as an approximate count ("~145 results").
A15: Oldest product on store | B15: Earliest product creation date in the Shopify catalog (Shopify stores only). A rough proxy for when the store went live.
A16: Domain registered | B16: Registration date of the website domain (RDAP). Not available for .ma domains from this environment.
A17: Ad Library link | B17: Opens the Page in the Meta Ad Library (all ads, Morocco).
A19: How the list was built
A20: Discovery | B20: 24 keyword searches in the Meta Ad Library, country Morocco, active ads: gummies, gummy, gummies cheveux, complément alimentaire, مكمل غذائي, حلوى الفيتامينات, فيتامينات, vitamines, collagène, كولاجين, ashwagandha, shilajit, biotine, magnésium, الدفع عند الاستلام فيتامين, gommes, oméga 3, créatine, whey maroc, زيادة الطول, and others. Advertisers were kept when they sell supplements or gummies AND are Moroccan (.ma domain, prices in MAD, Darija/COD wording or "Maroc" in the Page name). Foreign brands advertising into Morocco (Lashilé, Goli, iHerb...) were excluded.
A21: Excluded after checking | B21: Sukar By Lara (candy shop), Tisila (food), Beautyvana (skincare only), Hawta Maroc/Algoderm (general goods), Doppelherz (brand site, sells through pharmacies only), Marjane Mall (general marketplace).
A22: Limits | B22: Meta rate-limits the Ad Library heavily, and a few Pages may show no ad data. Ad counts change daily. Mapara, Maghreb Nutrition and Hoojan block automated visits (Cloudflare), so their prices are missing. Ad Library counts include all ad variations (dynamic creative), so a high count does not mean a high budget.
